{"150400": [{"kode_prop": "150000  ", "propinsi": "Prov. Kalimantan Selatan", "kode_kab_kota": "150400  ", "kabupaten_kota": "Kab. Tapin", "kode_kec": "150402  ", "kecamatan": "Kec. Tapin Selatan", "id": "40A6F552-30F5-E011-9CFC-5D2C9001E4E6", "npsn": "30301525", "sekolah": "SD NEGERI TAMBARANGAN 1", "bentuk": "SD", "status": "N", "alamat_jalan": "Jalan A. Yani KM. 105", "lintang": "-3.0004000", "bujur": "115.1279000"}, {"kode_prop": "150000  ", "propinsi": "Prov. Kalimantan Selatan", "kode_kab_kota": "150400  ", "kabupaten_kota": "Kab. Tapin", "kode_kec": "150403  ", "kecamatan": "Kec. Tapin Tengah", "id": "00C7F652-30F5-E011-A602-314C6C8C9A68", "npsn": "30301458", "sekolah": "SD NEGERI PANDULANGAN 1", "bentuk": "SD", "status": "N", "alamat_jalan": "Jl. Pangeran Suryanata", "lintang": "-2.9782000", "bujur": "115.0927000"}, {"kode_prop": "150000  ", "propinsi": "Prov. Kalimantan Selatan", "kode_kab_kota": "150400  ", "kabupaten_kota": "Kab. Tapin", "kode_kec": "150404  ", "kecamatan": "Kec. Bungur", "id": "E049F852-30F5-E011-9361-15449F764412", "npsn": "30301441", "sekolah": "SD NEGERI SABAH", "bentuk": "SD", "status": "N", "alamat_jalan": "Jl. Sododadi", "lintang": "-2.9811083", "bujur": "115.1713417"}, {"kode_prop": "150000  ", "propinsi": "Prov. Kalimantan Selatan", "kode_kab_kota": "150400  ", "kabupaten_kota": "Kab. Tapin", "kode_kec": "150405  ", "kecamatan": "Kec. Piani", "id": "70F5F852-30F5-E011-B3A4-15B80EEE7F72", "npsn": "30301561", "sekolah": "SD NEGERI BATUNG", "bentuk": "SD", "status": "N", "alamat_jalan": "Jl. Antilit", "lintang": "-2.9332000", "bujur": "115.4053000"}, {"kode_prop": "150000  ", "propinsi": "Prov. Kalimantan Selatan", "kode_kab_kota": "150400  ", "kabupaten_kota": "Kab. Tapin", "kode_kec": "150412  ", "kecamatan": "Kec. Salam Babaris", "id": "D0E6FC52-30F5-E011-8E02-39CD3CC53D95", "npsn": "30301455", "sekolah": "SD NEGERI PANTAI CABE", "bentuk": "SD", "status": "N", "alamat_jalan": "Jl. Transmigrasi Pantai Cabe", "lintang": "-3.0408000", "bujur": "115.1757000"}, {"kode_prop": "150000  ", "propinsi": "Prov. Kalimantan Selatan", "kode_kab_kota": "150400  ", "kabupaten_kota": "Kab. Tapin", "kode_kec": "150408  ", "kecamatan": "Kec. Bakarangan", "id": "3088FA52-30F5-E011-8E6E-933115EDC074", "npsn": "30301652", "sekolah": "SD NEGERI BUNDUNG 2", "bentuk": "SD", "status": "N", "alamat_jalan": "Jl. Bundung", "lintang": "-2.8998000", "bujur": "115.1343333"}, {"kode_prop": "150000  ", "propinsi": "Prov. Kalimantan Selatan", "kode_kab_kota": "150400  ", "kabupaten_kota": "Kab. Tapin", "kode_kec": "150410  ", "kecamatan": "Kec. Candi Laras Utara", "id": "E051FC52-30F5-E011-AA3C-91A9B9CC9EA8", "npsn": "30301565", "sekolah": "SD NEGERI BATALAS", "bentuk": "SD", "status": "N", "alamat_jalan": "Batalas Rt 01", "lintang": "-2.5707000", "bujur": "114.8627000"}, {"kode_prop": "150000  ", "propinsi": "Prov. Kalimantan Selatan", "kode_kab_kota": "150400  ", "kabupaten_kota": "Kab. Tapin", "kode_kec": "150402  ", "kecamatan": "Kec. Tapin Selatan", "id": "C048F652-30F5-E011-8CDF-735E791F7E33", "npsn": "30301625", "sekolah": "SD NEGERI LAWAHAN 2", "bentuk": "SD", "status": "N", "alamat_jalan": "Jalan Matang Asam Rt 01 Rw 01", "lintang": "-3.0371000", "bujur": "115.0890000"}, {"kode_prop": "150000  ", "propinsi": "Prov. Kalimantan Selatan", "kode_kab_kota": "150400  ", "kabupaten_kota": "Kab. Tapin", "kode_kec": "150404  ", "kecamatan": "Kec. Bungur", "id": "40A6F852-30F5-E011-9477-F54E582D143B", "npsn": "30301424", "sekolah": "SD NEGERI RANTAU BUJUR 2", "bentuk": "SD", "status": "N", "alamat_jalan": "Jl. Pir Nis 9c", "lintang": "-3.0183200", "bujur": "115.2383000"}, {"kode_prop": "150000  ", "propinsi": "Prov. Kalimantan Selatan", "kode_kab_kota": "150400  ", "kabupaten_kota": "Kab. Tapin", "kode_kec": "150410  ", "kecamatan": "Kec. Candi Laras Utara", "id": "80EF9A53-30F5-E011-BFA5-A32B6BF257C2", "npsn": "30315013", "sekolah": "SMP NEGERI 2 CANDI LARAS UTARA", "bentuk": "SMP", "status": "N", "alamat_jalan": "Jl.Telaga No.1 Rt.1", "lintang": "-2.7164000", "bujur": "114.9150000"}, {"kode_prop": "150000  ", "propinsi": "Prov. Kalimantan Selatan", "kode_kab_kota": "150400  ", "kabupaten_kota": "Kab. Tapin", "kode_kec": "150410  ", "kecamatan": "Kec. Candi Laras Utara", "id": "A0FC9A53-30F5-E011-9DE9-77F4B08940A6", "npsn": "30315018", "sekolah": "SMP NEGERI 3 CANDI LARAS UTARA", "bentuk": "SMP", "status": "N", "alamat_jalan": "Desa Kaladan Rt 05", "lintang": "-3.0076000", "bujur": "114.8510000"}, {"kode_prop": "150000  ", "propinsi": "Prov. Kalimantan Selatan", "kode_kab_kota": "150400  ", "kabupaten_kota": "Kab. Tapin", "kode_kec": "150406  ", "kecamatan": "Kec. Lokpaikat", "id": "2044F952-30F5-E011-93E6-45488F7210A9", "npsn": "30301556", "sekolah": "SD NEGERI BINDERANG", "bentuk": "SD", "status": "N", "alamat_jalan": "Jl. Brigjend H. Hasan Basry", "lintang": "-2.9070000", "bujur": "115.2046000"}, {"kode_prop": "150000  ", "propinsi": "Prov. Kalimantan Selatan", "kode_kab_kota": "150400  ", "kabupaten_kota": "Kab. Tapin", "kode_kec": "150411  ", "kecamatan": "Kec. Hatungun", "id": "E0FAFD52-30F5-E011-808F-A95BD4B228CE", "npsn": "30301481", "sekolah": "SD NEGERI MATANG BATAS", "bentuk": "SD", "status": "N", "alamat_jalan": "Jl. Batu Nyaring", "lintang": "-3.1641000", "bujur": "115.1389000"}, {"kode_prop": "150000  ", "propinsi": "Prov. Kalimantan Selatan", "kode_kab_kota": "150400  ", "kabupaten_kota": "Kab. Tapin", "kode_kec": "150411  ", "kecamatan": "Kec. Hatungun", "id": "F0B1FD52-30F5-E011-B26B-9DD130F67845", "npsn": "30301562", "sekolah": "SD NEGERI BATU HAPU 2", "bentuk": "SD", "status": "N", "alamat_jalan": "Jl. Muka Goa Batu Hapu", "lintang": "-3.1254000", "bujur": "115.1759000"}, {"kode_prop": "150000  ", "propinsi": "Prov. Kalimantan Selatan", "kode_kab_kota": "150400  ", "kabupaten_kota": "Kab. Tapin", "kode_kec": "150401  ", "kecamatan": "Kec. Binuang", "id": "104AF552-30F5-E011-94C5-E5844A54EFED", "npsn": "30301636", "sekolah": "SD NEGERI BINUANG 8", "bentuk": "SD", "status": "N", "alamat_jalan": "JL. TEMBOK BARU", "lintang": "-3.1584000", "bujur": "115.0836000"}, {"kode_prop": "150000  ", "propinsi": "Prov. Kalimantan Selatan", "kode_kab_kota": "150400  ", "kabupaten_kota": "Kab. Tapin", "kode_kec": "150401  ", "kecamatan": "Kec. Binuang", "id": "40D7AA53-30F5-E011-8B25-F9B6422029AB", "npsn": "30311938", "sekolah": "SMP ISLAM DARUL MUHIBBIEN", "bentuk": "SMP", "status": "S", "alamat_jalan": "Jl. A. Yani Km.84", "lintang": "-3.1665000", "bujur": "115.0860000"}, {"kode_prop": "150000  ", "propinsi": "Prov. Kalimantan Selatan", "kode_kab_kota": "150400  ", "kabupaten_kota": "Kab. Tapin", "kode_kec": "150403  ", "kecamatan": "Kec. Tapin Tengah", "id": "60F0F652-30F5-E011-ADAB-15D1C084EBA3", "npsn": "30301523", "sekolah": "SD NEGERI SERAWI", "bentuk": "SD", "status": "N", "alamat_jalan": "Serawi", "lintang": "-2.9416000", "bujur": "115.1112000"}, {"kode_prop": "150000  ", "propinsi": "Prov. Kalimantan Selatan", "kode_kab_kota": "150400  ", "kabupaten_kota": "Kab. Tapin", "kode_kec": "150402  ", "kecamatan": "Kec. Tapin Selatan", "id": "E084A6BD-A94D-4DB0-ABEE-A8D980FF2C5C", "npsn": "30301488", "sekolah": "SMKN 1 TAPIN SELATAN", "bentuk": "SMK", "status": "N", "alamat_jalan": "JL. SRAGEN", "lintang": "-2.9964000", "bujur": "115.1558000"}, {"kode_prop": "150000  ", "propinsi": "Prov. Kalimantan Selatan", "kode_kab_kota": "150400  ", "kabupaten_kota": "Kab. Tapin", "kode_kec": "150403  ", "kecamatan": "Kec. Tapin Tengah", "id": "908FF752-30F5-E011-9DA8-73DFE335A6BC", "npsn": "30301460", "sekolah": "SD NEGERI PANDAHAN 1", "bentuk": "SD", "status": "N", "alamat_jalan": "Jl. Raya Hakim Samad", "lintang": "-2.9345000", "bujur": "115.0840000"}, {"kode_prop": "150000  ", "propinsi": "Prov. Kalimantan Selatan", "kode_kab_kota": "150400  ", "kabupaten_kota": "Kab. Tapin", "kode_kec": "150403  ", "kecamatan": "Kec. Tapin Tengah", "id": "00B7F752-30F5-E011-9093-7742C89F6BCB", "npsn": "30301459", "sekolah": "SD NEGERI PANDAHAN 2", "bentuk": "SD", "status": "N", "alamat_jalan": "Jalan Hakim Samad", "lintang": "-2.9385000", "bujur": "115.0797000"}, {"kode_prop": "150000  ", "propinsi": "Prov. Kalimantan Selatan", "kode_kab_kota": "150400  ", "kabupaten_kota": "Kab. Tapin", "kode_kec": "150401  ", "kecamatan": "Kec. Binuang", "id": "B008F552-30F5-E011-A8AC-E15F53D574D8", "npsn": "30301599", "sekolah": "SD NEGERI BINUANG 10", "bentuk": "SD", "status": "N", "alamat_jalan": "Jl. Ray 4 Cempaka", "lintang": "-3.1115000", "bujur": "115.0381000"}, {"kode_prop": "150000  ", "propinsi": "Prov. Kalimantan Selatan", "kode_kab_kota": "150400  ", "kabupaten_kota": "Kab. Tapin", "kode_kec": "150412  ", "kecamatan": "Kec. Salam Babaris", "id": "A0C9FC52-30F5-E011-808A-A533E7F1F42F", "npsn": "30301604", "sekolah": "SD NEGERI KEMBANG HABANG 2", "bentuk": "SD", "status": "N", "alamat_jalan": "Jalan Datu sanggul", "lintang": "-3.0810000", "bujur": "115.1504000"}, {"kode_prop": "150000  ", "propinsi": "Prov. Kalimantan Selatan", "kode_kab_kota": "150400  ", "kabupaten_kota": "Kab. Tapin", "kode_kec": "150404  ", "kecamatan": "Kec. Bungur", "id": "805F9A53-30F5-E011-871A-3324FA64599B", "npsn": "30311936", "sekolah": "SMP NEGERI 2 BUNGUR", "bentuk": "SMP", "status": "N", "alamat_jalan": "Jl. Bendungan Irigasi", "lintang": "-3.0043667", "bujur": "115.2369900"}, {"kode_prop": "150000  ", "propinsi": "Prov. Kalimantan Selatan", "kode_kab_kota": "150400  ", "kabupaten_kota": "Kab. Tapin", "kode_kec": "150410  ", "kecamatan": "Kec. Candi Laras Utara", "id": "40E9FB52-30F5-E011-BE61-FDAAEEADBF13", "npsn": "30301531", "sekolah": "SD NEGERI TELUK HAUR", "bentuk": "SD", "status": "N", "alamat_jalan": "Teluk Haur", "lintang": "-2.8017000", "bujur": "114.8998000"}, {"kode_prop": "150000  ", "propinsi": "Prov. Kalimantan Selatan", "kode_kab_kota": "150400  ", "kabupaten_kota": "Kab. Tapin", "kode_kec": "150406  ", "kecamatan": "Kec. Lokpaikat", "id": "4079F952-30F5-E011-9B55-57F335D3058F", "npsn": "30301633", "sekolah": "SD NEGERI BITAHAN 2", "bentuk": "SD", "status": "N", "alamat_jalan": "Jl. Translok", "lintang": "-2.9265000", "bujur": "115.1830000"}, {"kode_prop": "150000  ", "propinsi": "Prov. Kalimantan Selatan", "kode_kab_kota": "150400  ", "kabupaten_kota": "Kab. Tapin", "kode_kec": "150406  ", "kecamatan": "Kec. Lokpaikat", "id": "306CF952-30F5-E011-AA91-E71453CD6DA1", "npsn": "30301621", "sekolah": "SD NEGERI LOKPAIKAT 3", "bentuk": "SD", "status": "N", "alamat_jalan": "Dusun Jadi Makmur", "lintang": "-2.9052000", "bujur": "115.2285000"}, {"kode_prop": "150000  ", "propinsi": "Prov. Kalimantan Selatan", "kode_kab_kota": "150400  ", "kabupaten_kota": "Kab. Tapin", "kode_kec": "150412  ", "kecamatan": "Kec. Salam Babaris", "id": "400A9B53-30F5-E011-8BD9-F7A819245376", "npsn": "30301483", "sekolah": "SMP NEGERI 2 SALAM BABARIS", "bentuk": "SMP", "status": "N", "alamat_jalan": "Jl. Datu Nuraya Km.10", "lintang": "-3.0741000", "bujur": "115.0810000"}, {"kode_prop": "150000  ", "propinsi": "Prov. Kalimantan Selatan", "kode_kab_kota": "150400  ", "kabupaten_kota": "Kab. Tapin", "kode_kec": "150406  ", "kecamatan": "Kec. Lokpaikat", "id": "8051F952-30F5-E011-9CB0-7FD191E99CFE", "npsn": "30301622", "sekolah": "SD NEGERI LOKPAIKAT 1", "bentuk": "SD", "status": "N", "alamat_jalan": "Jl. Brigjend H. Hasan Basry", "lintang": "-2.8932000", "bujur": "115.2121000"}, {"kode_prop": "150000  ", "propinsi": "Prov. Kalimantan Selatan", "kode_kab_kota": "150400  ", "kabupaten_kota": "Kab. Tapin", "kode_kec": "150408  ", "kecamatan": "Kec. Bakarangan", "id": "00BB9A53-30F5-E011-9936-7F74CB664995", "npsn": "30312545", "sekolah": "SMP NEGERI 2 BAKARANGAN", "bentuk": "SMP", "status": "N", "alamat_jalan": "Bundung", "lintang": "-2.8951550", "bujur": "115.1389417"}, {"kode_prop": "150000  ", "propinsi": "Prov. Kalimantan Selatan", "kode_kab_kota": "150400  ", "kabupaten_kota": "Kab. Tapin", "kode_kec": "150407  ", "kecamatan": "Kec. Tapin Utara", "id": "D0C1F952-30F5-E011-B260-759907BCE903", "npsn": "30301431", "sekolah": "SD NEGERI RANGDA MALINGKUNG 1", "bentuk": "SD", "status": "N", "alamat_jalan": "Jl. Brigjend. H. Hasan Basri", "lintang": "-2.9326700", "bujur": "115.1516283"}, {"kode_prop": "150000  ", "propinsi": "Prov. Kalimantan Selatan", "kode_kab_kota": "150400  ", "kabupaten_kota": "Kab. Tapin", "kode_kec": "150401  ", "kecamatan": "Kec. Binuang", "id": "8093F452-30F5-E011-853A-53F2C16DBA96", "npsn": "30301640", "sekolah": "SD NEGERI BINUANG 4", "bentuk": "SD", "status": "N", "alamat_jalan": "Jl. Raya Timur", "lintang": "-3.1575000", "bujur": "115.0911000"}, {"kode_prop": "150000  ", "propinsi": "Prov. Kalimantan Selatan", "kode_kab_kota": "150400  ", "kabupaten_kota": "Kab. Tapin", "kode_kec": "150401  ", "kecamatan": "Kec. Binuang", "id": "0057F552-30F5-E011-9054-219E555005C6", "npsn": "30301452", "sekolah": "SD NEGERI PUALAMSARI 3", "bentuk": "SD", "status": "N", "alamat_jalan": "Jl. Desa 12 Pir", "lintang": "-3.1334000", "bujur": "115.1085000"}, {"kode_prop": "150000  ", "propinsi": "Prov. Kalimantan Selatan", "kode_kab_kota": "150400  ", "kabupaten_kota": "Kab. Tapin", "kode_kec": "150402  ", "kecamatan": "Kec. Tapin Selatan", "id": "0080F652-30F5-E011-B796-4198E62AB3CD", "npsn": "30301443", "sekolah": "SD NEGERI RUMINTIN 2", "bentuk": "SD", "status": "N", "alamat_jalan": "Jl. Kumpai", "lintang": "-3.0136000", "bujur": "115.1051000"}, {"kode_prop": "150000  ", "propinsi": "Prov. Kalimantan Selatan", "kode_kab_kota": "150400  ", "kabupaten_kota": "Kab. Tapin", "kode_kec": "150405  ", "kecamatan": "Kec. Piani", "id": "4002F952-30F5-E011-8930-B1CE7DA133E7", "npsn": "30301542", "sekolah": "SD NEGERI BALAWAIAN", "bentuk": "SD", "status": "N", "alamat_jalan": "JL.BAGANDAH", "lintang": "-2.9128820", "bujur": "115.4316600"}, {"kode_prop": "150000  ", "propinsi": "Prov. Kalimantan Selatan", "kode_kab_kota": "150400  ", "kabupaten_kota": "Kab. Tapin", "kode_kec": "150409  ", "kecamatan": "Kec. Candi Laras Selatan", "id": "C0B3FB52-30F5-E011-A10A-A9DCE7FB0949", "npsn": "30301558", "sekolah": "SD NEGERI BERINGIN 2", "bentuk": "SD", "status": "N", "alamat_jalan": "Jalan Pelabuhan Margasari", "lintang": "-2.8822000", "bujur": "114.9360000"}, {"kode_prop": "150000  ", "propinsi": "Prov. Kalimantan Selatan", "kode_kab_kota": "150400  ", "kabupaten_kota": "Kab. Tapin", "kode_kec": "150403  ", "kecamatan": "Kec. Tapin Tengah", "id": "60FDF652-30F5-E011-87BF-F7A737B50A26", "npsn": "30301473", "sekolah": "SD NEGERI PEMATANG KARANGAN HULU", "bentuk": "SD", "status": "N", "alamat_jalan": "Jl. Pembangunan No.42 Tambaruntung", "lintang": "-2.9539000", "bujur": "115.1017000"}, {"kode_prop": "150000  ", "propinsi": "Prov. Kalimantan Selatan", "kode_kab_kota": "150400  ", "kabupaten_kota": "Kab. Tapin", "kode_kec": "150412  ", "kecamatan": "Kec. Salam Babaris", "id": "C05AFD52-30F5-E011-AC46-EBA7CF82D7EC", "npsn": "30301605", "sekolah": "SD NEGERI KEMBANG HABANG 1", "bentuk": "SD", "status": "N", "alamat_jalan": "Desa Kembang Habang Lama Nes 16 a", "lintang": "-3.0741000", "bujur": "115.0811000"}, {"kode_prop": "150000  ", "propinsi": "Prov. Kalimantan Selatan", "kode_kab_kota": "150400  ", "kabupaten_kota": "Kab. Tapin", "kode_kec": "150408  ", "kecamatan": "Kec. Bakarangan", "id": "00FAFA52-30F5-E011-9D58-7F28C24BF59D", "npsn": "30305442", "sekolah": "SD NEGERI PARIGI KACIL", "bentuk": "SD", "status": "N", "alamat_jalan": "Parigi Kacil", "lintang": "-2.9265533", "bujur": "115.0957633"}, {"kode_prop": "150000  ", "propinsi": "Prov. Kalimantan Selatan", "kode_kab_kota": "150400  ", "kabupaten_kota": "Kab. Tapin", "kode_kec": "150401  ", "kecamatan": "Kec. Binuang", "id": "B086F452-30F5-E011-8EBB-F380CD39E7F8", "npsn": "30301540", "sekolah": "SD NEGERI BINUANG 1", "bentuk": "SD", "status": "N", "alamat_jalan": "Jl. Tapioka Binuang", "lintang": "-3.1543000", "bujur": "115.0908000"}, {"kode_prop": "150000  ", "propinsi": "Prov. Kalimantan Selatan", "kode_kab_kota": "150400  ", "kabupaten_kota": "Kab. Tapin", "kode_kec": "150402  ", "kecamatan": "Kec. Tapin Selatan", "id": "00F7F552-30F5-E011-8740-0F8BB6050F09", "npsn": "30301530", "sekolah": "SD NEGERI TIMBAAN 1", "bentuk": "SD", "status": "N", "alamat_jalan": "Jl. Timbaan", "lintang": "-2.9745000", "bujur": "115.1180000"}, {"kode_prop": "150000  ", "propinsi": "Prov. Kalimantan Selatan", "kode_kab_kota": "150400  ", "kabupaten_kota": "Kab. Tapin", "kode_kec": "150401  ", "kecamatan": "Kec. Binuang", "id": "8CF45CF7-EC18-49D0-810C-6D9D02F97306", "npsn": "30301493", "sekolah": "SMAN 1 BINUANG", "bentuk": "SMA", "status": "N", "alamat_jalan": "JL JEND. A. YANI NO. 27 BINUANG", "lintang": "-3.1393000", "bujur": "115.0835000"}, {"kode_prop": "150000  ", "propinsi": "Prov. Kalimantan Selatan", "kode_kab_kota": "150400  ", "kabupaten_kota": "Kab. Tapin", "kode_kec": "150403  ", "kecamatan": "Kec. Tapin Tengah", "id": "6031F752-30F5-E011-BCCF-21BB25D583AF", "npsn": "30301475", "sekolah": "SD NEGERI PEMATANG KARANGAN HILIR 1", "bentuk": "SD", "status": "N", "alamat_jalan": "Jl. Hakim Samad", "lintang": "-2.9285000", "bujur": "115.0729000"}, {"kode_prop": "150000  ", "propinsi": "Prov. Kalimantan Selatan", "kode_kab_kota": "150400  ", "kabupaten_kota": "Kab. Tapin", "kode_kec": "150404  ", "kecamatan": "Kec. Bungur", "id": "5015F852-30F5-E011-B37C-750E48D261C1", "npsn": "30301654", "sekolah": "SD NEGERI BUNGUR BARU", "bentuk": "SD", "status": "N", "alamat_jalan": "Jl. Bungur Baru", "lintang": "-2.9570967", "bujur": "115.1463233"}, {"kode_prop": "150000  ", "propinsi": "Prov. Kalimantan Selatan", "kode_kab_kota": "150400  ", "kabupaten_kota": "Kab. Tapin", "kode_kec": "150412  ", "kecamatan": "Kec. Salam Babaris", "id": "C0189B53-30F5-E011-A2AC-9F850A863D6B", "npsn": "30301499", "sekolah": "SMP NEGERI 1 SALAM BABARIS", "bentuk": "SMP", "status": "N", "alamat_jalan": "Jl. TRANSMIGRASI", "lintang": "-3.0506000", "bujur": "115.1862000"}, {"kode_prop": "150000  ", "propinsi": "Prov. Kalimantan Selatan", "kode_kab_kota": "150400  ", "kabupaten_kota": "Kab. Tapin", "kode_kec": "150407  ", "kecamatan": "Kec. Tapin Utara", "id": "C87E27A1-C753-40FC-A0CF-E5C7E378DF84", "npsn": "69888869", "sekolah": "SDLBN LUMBU RAYA", "bentuk": "SDLB", "status": "N", "alamat_jalan": "JL.PERINTIS RAYA", "lintang": "-2.9245000", "bujur": "115.1549000"}, {"kode_prop": "150000  ", "propinsi": "Prov. Kalimantan Selatan", "kode_kab_kota": "150400  ", "kabupaten_kota": "Kab. Tapin", "kode_kec": "150402  ", "kecamatan": "Kec. Tapin Selatan", "id": "5004F652-30F5-E011-A569-47F86F3ADC6C", "npsn": "30301442", "sekolah": "SD NEGERI RUMINTIN 3", "bentuk": "SD", "status": "N", "alamat_jalan": "Desa Rumintin", "lintang": "-3.0260000", "bujur": "115.1454000"}, {"kode_prop": "150000  ", "propinsi": "Prov. Kalimantan Selatan", "kode_kab_kota": "150400  ", "kabupaten_kota": "Kab. Tapin", "kode_kec": "150402  ", "kecamatan": "Kec. Tapin Selatan", "id": "0012F652-30F5-E011-9EC9-9B6E4A84AA50", "npsn": "30301445", "sekolah": "SD NEGERI RUMINTIN 1", "bentuk": "SD", "status": "N", "alamat_jalan": "Jl.A.Yani Km 09", "lintang": "-3.0124000", "bujur": "115.1250000"}, {"kode_prop": "150000  ", "propinsi": "Prov. Kalimantan Selatan", "kode_kab_kota": "150400  ", "kabupaten_kota": "Kab. Tapin", "kode_kec": "150402  ", "kecamatan": "Kec. Tapin Selatan", "id": "3064F652-30F5-E011-AB1E-9541229A8D03", "npsn": "30301644", "sekolah": "SD NEGERI TANDUI 2", "bentuk": "SD", "status": "N", "alamat_jalan": "Jl. Datu Taming Karsa", "lintang": "-3.0582000", "bujur": "115.1109000"}, {"kode_prop": "150000  ", "propinsi": "Prov. Kalimantan Selatan", "kode_kab_kota": "150400  ", "kabupaten_kota": "Kab. Tapin", "kode_kec": "150402  ", "kecamatan": "Kec. Tapin Selatan", "id": "9E5B6679-5576-41BC-A664-B313F1747C44", "npsn": "30301490", "sekolah": "SMAN 1 TAPIN SELATAN", "bentuk": "SMA", "status": "N", "alamat_jalan": "JL. MUNGGU KAPASAN NO. 165", "lintang": "-3.0067000", "bujur": "115.1363000"}, {"kode_prop": "150000  ", "propinsi": "Prov. Kalimantan Selatan", "kode_kab_kota": "150400  ", "kabupaten_kota": "Kab. Tapin", "kode_kec": "150409  ", "kecamatan": "Kec. Candi Laras Selatan", "id": "6099FB52-30F5-E011-B364-C34A30BB7A30", "npsn": "30301656", "sekolah": "SD NEGERI CANDI LARAS", "bentuk": "SD", "status": "N", "alamat_jalan": "Jalan Candi Laras RT. 03", "lintang": "-2.8718000", "bujur": "114.9363000"}, {"kode_prop": "150000  ", "propinsi": "Prov. Kalimantan Selatan", "kode_kab_kota": "150400  ", "kabupaten_kota": "Kab. Tapin", "kode_kec": "150408  ", "kecamatan": "Kec. Bakarangan", "id": "10D1FA52-30F5-E011-A52F-03DBDBE9D242", "npsn": "30301468", "sekolah": "SD NEGERI PARIGI SIMBAR", "bentuk": "SD", "status": "N", "alamat_jalan": "Jl. Parigi Simbar", "lintang": "-2.9269700", "bujur": "115.1077767"}, {"kode_prop": "150000  ", "propinsi": "Prov. Kalimantan Selatan", "kode_kab_kota": "150400  ", "kabupaten_kota": "Kab. Tapin", "kode_kec": "150401  ", "kecamatan": "Kec. Binuang", "id": "801D9A53-30F5-E011-B160-7DD08E38F580", "npsn": "30301498", "sekolah": "SMP NEGERI 2 BINUANG", "bentuk": "SMP", "status": "N", "alamat_jalan": "Jl. Nes XI", "lintang": "-3.1038000", "bujur": "115.0885000"}, {"kode_prop": "150000  ", "propinsi": "Prov. Kalimantan Selatan", "kode_kab_kota": "150400  ", "kabupaten_kota": "Kab. Tapin", "kode_kec": "150401  ", "kecamatan": "Kec. Binuang", "id": "203DF552-30F5-E011-A01A-4F4327E7B102", "npsn": "30301649", "sekolah": "SD NEGERI GUNUNG BATU", "bentuk": "SD", "status": "N", "alamat_jalan": "Jl. Sarang Burung", "lintang": "-3.1766000", "bujur": "115.1069000"}, {"kode_prop": "150000  ", "propinsi": "Prov. Kalimantan Selatan", "kode_kab_kota": "150400  ", "kabupaten_kota": "Kab. Tapin", "kode_kec": "150401  ", "kecamatan": "Kec. Binuang", "id": "307EF552-30F5-E011-9E54-D773606E7CA3", "npsn": "30301511", "sekolah": "SD NEGERI TUNGKAP 2", "bentuk": "SD", "status": "N", "alamat_jalan": "Jl. Saka permai", "lintang": "-3.1715000", "bujur": "115.0773000"}, {"kode_prop": "150000  ", "propinsi": "Prov. Kalimantan Selatan", "kode_kab_kota": "150400  ", "kabupaten_kota": "Kab. Tapin", "kode_kec": "150401  ", "kecamatan": "Kec. Binuang", "id": "F0A0811B-3174-4134-8282-66E81125265A", "npsn": "30314201", "sekolah": "SMKN 1 BINUANG", "bentuk": "SMK", "status": "N", "alamat_jalan": "OSCAR", "lintang": "-3.1503330", "bujur": "115.1022680"}, {"kode_prop": "150000  ", "propinsi": "Prov. Kalimantan Selatan", "kode_kab_kota": "150400  ", "kabupaten_kota": "Kab. Tapin", "kode_kec": "150412  ", "kecamatan": "Kec. Salam Babaris", "id": "C021FD52-30F5-E011-90B9-1FA027B04BB4", "npsn": "30305441", "sekolah": "SD NEGERI SWATO BARU", "bentuk": "SD", "status": "N", "alamat_jalan": "Jl. Transmigrasi", "lintang": "-3.0599000", "bujur": "115.1865000"}, {"kode_prop": "150000  ", "propinsi": "Prov. Kalimantan Selatan", "kode_kab_kota": "150400  ", "kabupaten_kota": "Kab. Tapin", "kode_kec": "150409  ", "kecamatan": "Kec. Candi Laras Selatan", "id": "40D59A53-30F5-E011-8872-17BC518F3B3D", "npsn": "30301501", "sekolah": "SMP NEGERI 2 CANDI LARAS SELATAN", "bentuk": "SMP", "status": "N", "alamat_jalan": "Jl. Margasari Km.20", "lintang": "-2.8581000", "bujur": "115.0185000"}, {"kode_prop": "150000  ", "propinsi": "Prov. Kalimantan Selatan", "kode_kab_kota": "150400  ", "kabupaten_kota": "Kab. Tapin", "kode_kec": "150409  ", "kecamatan": "Kec. Candi Laras Selatan", "id": "E0C0FB52-30F5-E011-9104-73D3A31C5B9B", "npsn": "30301464", "sekolah": "SD NEGERI PABAUNGAN HILIR 2", "bentuk": "SD", "status": "N", "alamat_jalan": "jl. Norsitiwana Desa Pabaungan Hilir Rt.07", "lintang": "-2.8418000", "bujur": "115.0010000"}, {"kode_prop": "150000  ", "propinsi": "Prov. Kalimantan Selatan", "kode_kab_kota": "150400  ", "kabupaten_kota": "Kab. Tapin", "kode_kec": "150411  ", "kecamatan": "Kec. Hatungun", "id": "C069FD52-30F5-E011-97EA-A38A77C7141A", "npsn": "30301628", "sekolah": "SD NEGERI HATUNGUN 1", "bentuk": "SD", "status": "N", "alamat_jalan": "Jl. Raya Timur Km.10", "lintang": "-3.1447000", "bujur": "115.1657000"}, {"kode_prop": "150000  ", "propinsi": "Prov. Kalimantan Selatan", "kode_kab_kota": "150400  ", "kabupaten_kota": "Kab. Tapin", "kode_kec": "150407  ", "kecamatan": "Kec. Tapin Utara", "id": "7039FA52-30F5-E011-B398-D545490BAE06", "npsn": "30301602", "sekolah": "SD NEGERI KUPANG 1", "bentuk": "SD", "status": "N", "alamat_jalan": "Kupang", "lintang": "-2.9479050", "bujur": "115.1466950"}, {"kode_prop": "150000  ", "propinsi": "Prov. Kalimantan Selatan", "kode_kab_kota": "150400  ", "kabupaten_kota": "Kab. Tapin", "kode_kec": "150407  ", "kecamatan": "Kec. Tapin Utara", "id": "D060FA52-30F5-E011-AEA6-B7DF67367051", "npsn": "30301548", "sekolah": "SD NEGERI ANTASARI HILIR", "bentuk": "SD", "status": "N", "alamat_jalan": "Jl. Antasari", "lintang": "-2.9361300", "bujur": "115.1281233"}, {"kode_prop": "150000  ", "propinsi": "Prov. Kalimantan Selatan", "kode_kab_kota": "150400  ", "kabupaten_kota": "Kab. Tapin", "kode_kec": "150411  ", "kecamatan": "Kec. Hatungun", "id": "00CFFD52-30F5-E011-9C16-FDBE29B6D70D", "npsn": "30301627", "sekolah": "SD NEGERI HATUNGUN 2", "bentuk": "SD", "status": "N", "alamat_jalan": "Hatungun Rt 1", "lintang": "-3.1389000", "bujur": "115.1680000"}, {"kode_prop": "150000  ", "propinsi": "Prov. Kalimantan Selatan", "kode_kab_kota": "150400  ", "kabupaten_kota": "Kab. Tapin", "kode_kec": "150402  ", "kecamatan": "Kec. Tapin Selatan", "id": "40C1F552-30F5-E011-82EE-43767674AC8D", "npsn": "30301514", "sekolah": "SD NEGERI SWATO TATAKAN 1", "bentuk": "SD", "status": "N", "alamat_jalan": "Jl. A.yani", "lintang": "-3.0575000", "bujur": "115.1169000"}, {"kode_prop": "150000  ", "propinsi": "Prov. Kalimantan Selatan", "kode_kab_kota": "150400  ", "kabupaten_kota": "Kab. Tapin", "kode_kec": "150410  ", "kecamatan": "Kec. Candi Laras Utara", "id": "0093FC52-30F5-E011-8AF0-9B57D9D28ADA", "npsn": "30301446", "sekolah": "SD NEGERI RAWANA HULU", "bentuk": "SD", "status": "N", "alamat_jalan": "Ds. Rawana Hulu", "lintang": "-2.7760000", "bujur": "114.9731000"}, {"kode_prop": "150000  ", "propinsi": "Prov. Kalimantan Selatan", "kode_kab_kota": "150400  ", "kabupaten_kota": "Kab. Tapin", "kode_kec": "150404  ", "kecamatan": "Kec. Bungur", "id": "4071F852-30F5-E011-8BB0-2D3729D37818", "npsn": "30301623", "sekolah": "SD NEGERI LINUH 2", "bentuk": "SD", "status": "N", "alamat_jalan": "Desa Linuh", "lintang": "-3.0041000", "bujur": "115.2368750"}, {"kode_prop": "150000  ", "propinsi": "Prov. Kalimantan Selatan", "kode_kab_kota": "150400  ", "kabupaten_kota": "Kab. Tapin", "kode_kec": "150412  ", "kecamatan": "Kec. Salam Babaris", "id": "A04CFD52-30F5-E011-8CFF-E3B2C841600D", "npsn": "30301515", "sekolah": "SD NEGERI SWATO 3", "bentuk": "SD", "status": "N", "alamat_jalan": "NES 8 B", "lintang": "-3.0285000", "bujur": "115.1190000"}, {"kode_prop": "150000  ", "propinsi": "Prov. Kalimantan Selatan", "kode_kab_kota": "150400  ", "kabupaten_kota": "Kab. Tapin", "kode_kec": "150403  ", "kecamatan": "Kec. Tapin Tengah", "id": "3054F752-30F5-E011-973E-07B758E154CF", "npsn": "30301612", "sekolah": "SD NEGERI HIYUNG 1", "bentuk": "SD", "status": "N", "alamat_jalan": "Jl. Hakim Samad km 14", "lintang": "-2.8933000", "bujur": "115.0524000"}, {"kode_prop": "150000  ", "propinsi": "Prov. Kalimantan Selatan", "kode_kab_kota": "150400  ", "kabupaten_kota": "Kab. Tapin", "kode_kec": "150409  ", "kecamatan": "Kec. Candi Laras Selatan", "id": "9064FB52-30F5-E011-B4FA-D7DB9620F32E", "npsn": "30301521", "sekolah": "SD NEGERI SUNGAI RUTAS 1", "bentuk": "SD", "status": "N", "alamat_jalan": "Jl. Margasari Km.18", "lintang": "-2.8610000", "bujur": "115.0258000"}, {"kode_prop": "150000  ", "propinsi": "Prov. Kalimantan Selatan", "kode_kab_kota": "150400  ", "kabupaten_kota": "Kab. Tapin", "kode_kec": "150407  ", "kecamatan": "Kec. Tapin Utara", "id": "50DCF952-30F5-E011-AB0E-8910A4E59428", "npsn": "30301430", "sekolah": "SD NEGERI RANGDA MALINGKUNG 3", "bentuk": "SD", "status": "N", "alamat_jalan": "Jl. PGA Rantau", "lintang": "-2.9350983", "bujur": "115.1525167"}, {"kode_prop": "150000  ", "propinsi": "Prov. Kalimantan Selatan", "kode_kab_kota": "150400  ", "kabupaten_kota": "Kab. Tapin", "kode_kec": "150407  ", "kecamatan": "Kec. Tapin Utara", "id": "A0E9F952-30F5-E011-875F-159D3A5DFDFD", "npsn": "30301429", "sekolah": "SD NEGERI RANGDA MALINGKUNG 4", "bentuk": "SD", "status": "N", "alamat_jalan": "Jl.penghulu", "lintang": "-2.9389633", "bujur": "115.1634017"}, {"kode_prop": "150000  ", "propinsi": "Prov. Kalimantan Selatan", "kode_kab_kota": "150400  ", "kabupaten_kota": "Kab. Tapin", "kode_kec": "150404  ", "kecamatan": "Kec. Bungur", "id": "A07EF852-30F5-E011-8A9F-E36C33670823", "npsn": "30301648", "sekolah": "SD NEGERI HANGUI 1", "bentuk": "SD", "status": "N", "alamat_jalan": "JL. AIR TERJUN DESA HANGUI", "lintang": "-3.0074200", "bujur": "115.2613320"}, {"kode_prop": "150000  ", "propinsi": "Prov. Kalimantan Selatan", "kode_kab_kota": "150400  ", "kabupaten_kota": "Kab. Tapin", "kode_kec": "150412  ", "kecamatan": "Kec. Salam Babaris", "id": "E0BAFC52-30F5-E011-9B8A-E1CC39AE2765", "npsn": "30301568", "sekolah": "SD NEGERI SALAM BABARIS 4", "bentuk": "SD", "status": "N", "alamat_jalan": "Desa Salam Babaris", "lintang": "-3.0036000", "bujur": "115.1337000"}, {"kode_prop": "150000  ", "propinsi": "Prov. Kalimantan Selatan", "kode_kab_kota": "150400  ", "kabupaten_kota": "Kab. Tapin", "kode_kec": "150401  ", "kecamatan": "Kec. Binuang", "id": "80E1F452-30F5-E011-9E9D-DB0814B50EC9", "npsn": "30301512", "sekolah": "SD NEGERI TUNGKAP 1", "bentuk": "SD", "status": "N", "alamat_jalan": "Jl. A. Yani Km 83 Tungkap", "lintang": "-3.1686000", "bujur": "115.0839000"}, {"kode_prop": "150000  ", "propinsi": "Prov. Kalimantan Selatan", "kode_kab_kota": "150400  ", "kabupaten_kota": "Kab. Tapin", "kode_kec": "150402  ", "kecamatan": "Kec. Tapin Selatan", "id": "20DCF552-30F5-E011-A9D9-695E9220E90C", "npsn": "30301646", "sekolah": "SD NEGERI HARAPAN MASA 1", "bentuk": "SD", "status": "N", "alamat_jalan": "Jl. A. Yani Km 107", "lintang": "-2.9849000", "bujur": "115.1346000"}, {"kode_prop": "150000  ", "propinsi": "Prov. Kalimantan Selatan", "kode_kab_kota": "150400  ", "kabupaten_kota": "Kab. Tapin", "kode_kec": "150409  ", "kecamatan": "Kec. Candi Laras Selatan", "id": "E021FB52-30F5-E011-9DFD-C12A60D0A080", "npsn": "30301557", "sekolah": "SD NEGERI BERINGIN B", "bentuk": "SD", "status": "N", "alamat_jalan": "Beringin Barat Rt.1", "lintang": "-2.8788000", "bujur": "114.9368000"}, {"kode_prop": "150000  ", "propinsi": "Prov. Kalimantan Selatan", "kode_kab_kota": "150400  ", "kabupaten_kota": "Kab. Tapin", "kode_kec": "150407  ", "kecamatan": "Kec. Tapin Utara", "id": "B004FA52-30F5-E011-809F-7185FB3A93DF", "npsn": "30301541", "sekolah": "SD NEGERI BANUA HALAT KANAN", "bentuk": "SD", "status": "N", "alamat_jalan": "Jl. Perintis Raya Km.3", "lintang": "-2.9107267", "bujur": "115.1531083"}, {"kode_prop": "150000  ", "propinsi": "Prov. Kalimantan Selatan", "kode_kab_kota": "150400  ", "kabupaten_kota": "Kab. Tapin", "kode_kec": "150401  ", "kecamatan": "Kec. Binuang", "id": "6071F552-30F5-E011-B5E1-7F6AEF09AA01", "npsn": "30301453", "sekolah": "SD NEGERI PUALAMSARI 2", "bentuk": "SD", "status": "N", "alamat_jalan": "Jl. Merpati", "lintang": "-3.1533000", "bujur": "115.1002000"}, {"kode_prop": "150000  ", "propinsi": "Prov. Kalimantan Selatan", "kode_kab_kota": "150400  ", "kabupaten_kota": "Kab. Tapin", "kode_kec": "150407  ", "kecamatan": "Kec. Tapin Utara", "id": "A046FA52-30F5-E011-902C-15EC70E35F21", "npsn": "30301601", "sekolah": "SD NEGERI KUPANG 2", "bentuk": "SD", "status": "N", "alamat_jalan": "Jl. Jend A Yani Km.1", "lintang": "-2.9420217", "bujur": "115.1489650"}, {"kode_prop": "150000  ", "propinsi": "Prov. Kalimantan Selatan", "kode_kab_kota": "150400  ", "kabupaten_kota": "Kab. Tapin", "kode_kec": "150402  ", "kecamatan": "Kec. Tapin Selatan", "id": "D0CEF552-30F5-E011-9467-6F92EA34759A", "npsn": "30301534", "sekolah": "SD NEGERI TATAKAN 1", "bentuk": "SD", "status": "N", "alamat_jalan": "Tatakan", "lintang": "-3.0565000", "bujur": "115.1164000"}, {"kode_prop": "150000  ", "propinsi": "Prov. Kalimantan Selatan", "kode_kab_kota": "150400  ", "kabupaten_kota": "Kab. Tapin", "kode_kec": "150407  ", "kecamatan": "Kec. Tapin Utara", "id": "20A7F952-30F5-E011-8388-E5E2F4C0BBB3", "npsn": "30301436", "sekolah": "SD NEGERI RANTAU KIWA 1", "bentuk": "SD", "status": "N", "alamat_jalan": "Jl. Brigjen H.hasan Basry No.2", "lintang": "-2.9322117", "bujur": "115.1523033"}, {"kode_prop": "150000  ", "propinsi": "Prov. Kalimantan Selatan", "kode_kab_kota": "150400  ", "kabupaten_kota": "Kab. Tapin", "kode_kec": "150407  ", "kecamatan": "Kec. Tapin Utara", "id": "401FFA52-30F5-E011-A6C0-27F1E8A66244", "npsn": "30301553", "sekolah": "SD NEGERI BANUA HANYAR HULU", "bentuk": "SD", "status": "N", "alamat_jalan": "Jl. Perintis Raya Km.4", "lintang": "-2.9026033", "bujur": "115.1429550"}, {"kode_prop": "150000  ", "propinsi": "Prov. Kalimantan Selatan", "kode_kab_kota": "150400  ", "kabupaten_kota": "Kab. Tapin", "kode_kec": "150409  ", "kecamatan": "Kec. Candi Laras Selatan", "id": "A049FB52-30F5-E011-A1A3-0D329EA8277C", "npsn": "30301618", "sekolah": "SD NEGERI MARAMPIAU", "bentuk": "SD", "status": "N", "alamat_jalan": "Jl. Rantau Margasari Desa Marampiau Rt 5 No 27", "lintang": "-2.8682000", "bujur": "114.9819000"}, {"kode_prop": "150000  ", "propinsi": "Prov. Kalimantan Selatan", "kode_kab_kota": "150400  ", "kabupaten_kota": "Kab. Tapin", "kode_kec": "150403  ", "kecamatan": "Kec. Tapin Tengah", "id": "20D1F752-30F5-E011-9CE3-AB4A7CF6BCC7", "npsn": "30301539", "sekolah": "SD NEGERI SUNGAI BAHALANG", "bentuk": "SD", "status": "N", "alamat_jalan": "Jl. Transmigrasi", "lintang": "-2.9706000", "bujur": "115.0812000"}, {"kode_prop": "150000  ", "propinsi": "Prov. Kalimantan Selatan", "kode_kab_kota": "150400  ", "kabupaten_kota": "Kab. Tapin", "kode_kec": "150410  ", "kecamatan": "Kec. Candi Laras Utara", "id": "B02AFC52-30F5-E011-9561-1DA037E714D0", "npsn": "30301615", "sekolah": "SD NEGERI MARGASARI ILIR 2", "bentuk": "SD", "status": "N", "alamat_jalan": "Jl. Pendidikan Desa Margasari Ilir RT.01 RW.01", "lintang": "-2.8797000", "bujur": "114.9341000"}, {"kode_prop": "150000  ", "propinsi": "Prov. Kalimantan Selatan", "kode_kab_kota": "150400  ", "kabupaten_kota": "Kab. Tapin", "kode_kec": "150401  ", "kecamatan": "Kec. Binuang", "id": "8023F552-30F5-E011-830F-B96B584A80E9", "npsn": "30301551", "sekolah": "SD NEGERI A. YANI PURA 2", "bentuk": "SD", "status": "N", "alamat_jalan": "Jl. Patuakan", "lintang": "-3.1502000", "bujur": "115.1110000"}, {"kode_prop": "150000  ", "propinsi": "Prov. Kalimantan Selatan", "kode_kab_kota": "150400  ", "kabupaten_kota": "Kab. Tapin", "kode_kec": "150405  ", "kecamatan": "Kec. Piani", "id": "5C4312D3-09F3-438F-BBBE-FDFA8F95BF59", "npsn": "69896553", "sekolah": "SD NEGERI LALAPIN", "bentuk": "SD", "status": "N", "alamat_jalan": "Jalan Lalapin", "lintang": "-2.9068110", "bujur": "115.3816000"}, {"kode_prop": "150000  ", "propinsi": "Prov. Kalimantan Selatan", "kode_kab_kota": "150400  ", "kabupaten_kota": "Kab. Tapin", "kode_kec": "150403  ", "kecamatan": "Kec. Tapin Tengah", "id": "10D5F652-30F5-E011-8C84-7D87324BCA14", "npsn": "30301613", "sekolah": "SD NEGERI LABUNG 1", "bentuk": "SD", "status": "N", "alamat_jalan": "Jl. Simpang Tiga Labung", "lintang": "-2.9605000", "bujur": "115.1098000"}, {"kode_prop": "150000  ", "propinsi": "Prov. Kalimantan Selatan", "kode_kab_kota": "150400  ", "kabupaten_kota": "Kab. Tapin", "kode_kec": "150408  ", "kecamatan": "Kec. Bakarangan", "id": "50C3FA52-30F5-E011-A84B-0D911103BB2A", "npsn": "30301651", "sekolah": "SD NEGERI GADUNG HILIR", "bentuk": "SD", "status": "N", "alamat_jalan": "Jl. Syekh Salman Al Farisi", "lintang": "-2.8982650", "bujur": "115.1216250"}, {"kode_prop": "150000  ", "propinsi": "Prov. Kalimantan Selatan", "kode_kab_kota": "150400  ", "kabupaten_kota": "Kab. Tapin", "kode_kec": "150409  ", "kecamatan": "Kec. Candi Laras Selatan", "id": "232BFE02-7DC6-4C69-A04E-1800F8223551", "npsn": "30301492", "sekolah": "SMAN 1 CANDI LARAS SELATAN", "bentuk": "SMA", "status": "N", "alamat_jalan": "JL. MARGASARI KM. 27", "lintang": "-2.8785000", "bujur": "114.9620000"}, {"kode_prop": "150000  ", "propinsi": "Prov. Kalimantan Selatan", "kode_kab_kota": "150400  ", "kabupaten_kota": "Kab. Tapin", "kode_kec": "150409  ", "kecamatan": "Kec. Candi Laras Selatan", "id": "60CEFB52-30F5-E011-A83E-2B93541B0DDC", "npsn": "30301462", "sekolah": "SD NEGERI PABAUNGAN PANTAI", "bentuk": "SD", "status": "N", "alamat_jalan": "Jl. Pabaungan Pantai", "lintang": "-2.8276000", "bujur": "115.0205000"}, {"kode_prop": "150000  ", "propinsi": "Prov. Kalimantan Selatan", "kode_kab_kota": "150400  ", "kabupaten_kota": "Kab. Tapin", "kode_kec": "150401  ", "kecamatan": "Kec. Binuang", "id": "60A0F452-30F5-E011-AB15-5F40AC0D49EA", "npsn": "30305440", "sekolah": "SD NEGERI A. YANI PURA 1", "bentuk": "SD", "status": "N", "alamat_jalan": "Jl. Demak", "lintang": "-3.1568000", "bujur": "115.1020000"}, {"kode_prop": "150000  ", "propinsi": "Prov. Kalimantan Selatan", "kode_kab_kota": "150400  ", "kabupaten_kota": "Kab. Tapin", "kode_kec": "150405  ", "kecamatan": "Kec. Piani", "id": "80799A53-30F5-E011-A988-031C7B529597", "npsn": "30311961", "sekolah": "SMP NEGERI 2 PIANI", "bentuk": "SMP", "status": "N", "alamat_jalan": "Jl. Trans Kandangan Batulicin Km. 40", "lintang": "-2.9138000", "bujur": "115.3992000"}, {"kode_prop": "150000  ", "propinsi": "Prov. Kalimantan Selatan", "kode_kab_kota": "150400  ", "kabupaten_kota": "Kab. Tapin", "kode_kec": "150411  ", "kecamatan": "Kec. Hatungun", "id": "3095FD52-30F5-E011-9B46-4B501570AC24", "npsn": "30301655", "sekolah": "SD NEGERI BURAKAI", "bentuk": "SD", "status": "N", "alamat_jalan": "Jl. Burakai", "lintang": "-3.1424000", "bujur": "115.0902000"}, {"kode_prop": "150000  ", "propinsi": "Prov. Kalimantan Selatan", "kode_kab_kota": "150400  ", "kabupaten_kota": "Kab. Tapin", "kode_kec": "150401  ", "kecamatan": "Kec. Binuang", "id": "808CF552-30F5-E011-8764-7F74A6F48EBB", "npsn": "30301461", "sekolah": "SD NEGERI PADANG SARI", "bentuk": "SD", "status": "N", "alamat_jalan": "Jl. Pembangunan", "lintang": "-3.1243000", "bujur": "115.1220000"}, {"kode_prop": "150000  ", "propinsi": "Prov. Kalimantan Selatan", "kode_kab_kota": "150400  ", "kabupaten_kota": "Kab. Tapin", "kode_kec": "150406  ", "kecamatan": "Kec. Lokpaikat", "id": "A08CF952-30F5-E011-ADB6-E9821A135293", "npsn": "30301632", "sekolah": "SD NEGERI BITAHAN BARU", "bentuk": "SD", "status": "N", "alamat_jalan": "Jl. Bitahan Baru", "lintang": "-2.9541000", "bujur": "115.2045000"}, {"kode_prop": "150000  ", "propinsi": "Prov. Kalimantan Selatan", "kode_kab_kota": "150400  ", "kabupaten_kota": "Kab. Tapin", "kode_kec": "150401  ", "kecamatan": "Kec. Binuang", "id": "A0BCAA53-30F5-E011-9F8E-5DD49F7C59B2", "npsn": "30301487", "sekolah": "SMP KARTIKA V-4 BINUANG", "bentuk": "SMP", "status": "S", "alamat_jalan": "Jl. Raya Timur", "lintang": "-3.1570000", "bujur": "115.0912000"}, {"kode_prop": "150000  ", "propinsi": "Prov. Kalimantan Selatan", "kode_kab_kota": "150400  ", "kabupaten_kota": "Kab. Tapin", "kode_kec": "150407  ", "kecamatan": "Kec. Tapin Utara", "id": "B053FA52-30F5-E011-A89E-0327C742B8AE", "npsn": "30301549", "sekolah": "SD NEGERI ANTASARI", "bentuk": "SD", "status": "N", "alamat_jalan": "Jl. Anim Sahibar", "lintang": "-2.9333667", "bujur": "115.1370183"}, {"kode_prop": "150000  ", "propinsi": "Prov. Kalimantan Selatan", "kode_kab_kota": "150400  ", "kabupaten_kota": "Kab. Tapin", "kode_kec": "150403  ", "kecamatan": "Kec. Tapin Tengah", "id": "9017F752-30F5-E011-B015-6369F2298601", "npsn": "30301620", "sekolah": "SD NEGERI MANDURIAN", "bentuk": "SD", "status": "N", "alamat_jalan": "Mandurian", "lintang": "-2.9570000", "bujur": "115.1259000"}, {"kode_prop": "150000  ", "propinsi": "Prov. Kalimantan Selatan", "kode_kab_kota": "150400  ", "kabupaten_kota": "Kab. Tapin", "kode_kec": "150410  ", "kecamatan": "Kec. Candi Laras Utara", "id": "901DFC52-30F5-E011-89A1-3F45E9DAB392", "npsn": "30301552", "sekolah": "SD NEGERI SUNGAI SALAI HILIR", "bentuk": "SD", "status": "N", "alamat_jalan": "Sungai Salai Hilir", "lintang": "-2.9269000", "bujur": "114.8590000"}, {"kode_prop": "150000  ", "propinsi": "Prov. Kalimantan Selatan", "kode_kab_kota": "150400  ", "kabupaten_kota": "Kab. Tapin", "kode_kec": "150403  ", "kecamatan": "Kec. Tapin Tengah", "id": "E0379A53-30F5-E011-8434-F71A6F39141D", "npsn": "30301503", "sekolah": "SMP NEGERI 1 TAPIN TENGAH", "bentuk": "SMP", "status": "N", "alamat_jalan": "Jl. Pembangunan No.2", "lintang": "-2.9538000", "bujur": "115.1004000"}, {"kode_prop": "150000  ", "propinsi": "Prov. Kalimantan Selatan", "kode_kab_kota": "150400  ", "kabupaten_kota": "Kab. Tapin", "kode_kec": "150407  ", "kecamatan": "Kec. Tapin Utara", "id": "271D6242-E410-4402-AC4E-805FA6C229DE", "npsn": "30301489", "sekolah": "SMKN 1 RANTAU", "bentuk": "SMK", "status": "N", "alamat_jalan": "JL. GERILYA", "lintang": "-2.9265600", "bujur": "115.1439617"}, {"kode_prop": "150000  ", "propinsi": "Prov. Kalimantan Selatan", "kode_kab_kota": "150400  ", "kabupaten_kota": "Kab. Tapin", "kode_kec": "150412  ", "kecamatan": "Kec. Salam Babaris", "id": "65D71448-070B-4360-9862-97DBC8F03E7B", "npsn": "69757353", "sekolah": "SMAN 1 SALAM BABARIS", "bentuk": "SMA", "status": "N", "alamat_jalan": "JL.TRANSMIGASI UTARA NO. 212", "lintang": "-3.0490900", "bujur": "115.1883730"}, {"kode_prop": "150000  ", "propinsi": "Prov. Kalimantan Selatan", "kode_kab_kota": "150400  ", "kabupaten_kota": "Kab. Tapin", "kode_kec": "150407  ", "kecamatan": "Kec. Tapin Utara", "id": "D011FA52-30F5-E011-8A0E-1FD5D32FB82E", "npsn": "30301425", "sekolah": "SD NEGERI RANTAU KANAN 1", "bentuk": "SD", "status": "N", "alamat_jalan": "Jl. Darussalam", "lintang": "-2.9332250", "bujur": "115.1458000"}, {"kode_prop": "150000  ", "propinsi": "Prov. Kalimantan Selatan", "kode_kab_kota": "150400  ", "kabupaten_kota": "Kab. Tapin", "kode_kec": "150407  ", "kecamatan": "Kec. Tapin Utara", "id": "F0A09A53-30F5-E011-84F3-CDCF7969E2B4", "npsn": "30305510", "sekolah": "SMP NEGERI 2 RANTAU", "bentuk": "SMP", "status": "N", "alamat_jalan": "Jl. Gerilya Rantau", "lintang": "-2.9291950", "bujur": "115.1450983"}, {"kode_prop": "150000  ", "propinsi": "Prov. Kalimantan Selatan", "kode_kab_kota": "150400  ", "kabupaten_kota": "Kab. Tapin", "kode_kec": "150407  ", "kecamatan": "Kec. Tapin Utara", "id": "F0F6F952-30F5-E011-9676-D10A8025A3A2", "npsn": "30301472", "sekolah": "SD NEGERI PERINTIS RAYA", "bentuk": "SD", "status": "N", "alamat_jalan": "Jl. Perintis Raya", "lintang": "-2.9296667", "bujur": "115.1512967"}, {"kode_prop": "150000  ", "propinsi": "Prov. Kalimantan Selatan", "kode_kab_kota": "150400  ", "kabupaten_kota": "Kab. Tapin", "kode_kec": "150405  ", "kecamatan": "Kec. Piani", "id": "BC44EF76-6B83-4EAF-8855-A75461A0BE38", "npsn": "69896782", "sekolah": "SD NEGERI BALAWAIAN HILIR", "bentuk": "SD", "status": "N", "alamat_jalan": "Desa Balawaian", "lintang": null, "bujur": null}, {"kode_prop": "150000  ", "propinsi": "Prov. Kalimantan Selatan", "kode_kab_kota": "150400  ", "kabupaten_kota": "Kab. Tapin", "kode_kec": "150409  ", "kecamatan": "Kec. Candi Laras Selatan", "id": "20C89A53-30F5-E011-83B6-0B06DD642E12", "npsn": "30301509", "sekolah": "SMP NEGERI 1 CANDI LARAS SELATAN", "bentuk": "SMP", "status": "N", "alamat_jalan": "Jl. Pendidikan No.8", "lintang": "-2.8839000", "bujur": "114.9345000"}, {"kode_prop": "150000  ", "propinsi": "Prov. Kalimantan Selatan", "kode_kab_kota": "150400  ", "kabupaten_kota": "Kab. Tapin", "kode_kec": "150411  ", "kecamatan": "Kec. Hatungun", "id": "A0C0FD52-30F5-E011-A8E2-E1CFC573D55D", "npsn": "30301547", "sekolah": "SD NEGERI ASAM RANDAH", "bentuk": "SD", "status": "N", "alamat_jalan": "Jl. Karya Baru RT.06/RW.03", "lintang": "-3.1378230", "bujur": "115.2048000"}, {"kode_prop": "150000  ", "propinsi": "Prov. Kalimantan Selatan", "kode_kab_kota": "150400  ", "kabupaten_kota": "Kab. Tapin", "kode_kec": "150404  ", "kecamatan": "Kec. Bungur", "id": "6064F852-30F5-E011-AD51-4375E6540624", "npsn": "30301607", "sekolah": "SD NEGERI KALUMPANG 2", "bentuk": "SD", "status": "N", "alamat_jalan": "Jalan Sandar 16 B", "lintang": "-3.0165617", "bujur": "115.2015767"}, {"kode_prop": "150000  ", "propinsi": "Prov. Kalimantan Selatan", "kode_kab_kota": "150400  ", "kabupaten_kota": "Kab. Tapin", "kode_kec": "150408  ", "kecamatan": "Kec. Bakarangan", "id": "C0DEFA52-30F5-E011-AEFB-BD81BF6C8419", "npsn": "30301510", "sekolah": "SD NEGERI WARINGIN DALAM", "bentuk": "SD", "status": "N", "alamat_jalan": "Jl. Salman Al Parisi", "lintang": "-2.9093900", "bujur": "115.1184183"}, {"kode_prop": "150000  ", "propinsi": "Prov. Kalimantan Selatan", "kode_kab_kota": "150400  ", "kabupaten_kota": "Kab. Tapin", "kode_kec": "150405  ", "kecamatan": "Kec. Piani", "id": "30B3F852-30F5-E011-A438-3B4E390FF8E0", "npsn": "30301466", "sekolah": "SD NEGERI MIAWA", "bentuk": "SD", "status": "N", "alamat_jalan": "Jl. Pembangunan", "lintang": "-2.9582000", "bujur": "115.2760000"}, {"kode_prop": "150000  ", "propinsi": "Prov. Kalimantan Selatan", "kode_kab_kota": "150400  ", "kabupaten_kota": "Kab. Tapin", "kode_kec": "150404  ", "kecamatan": "Kec. Bungur", "id": "C08BF852-30F5-E011-A60A-E399BFFB1D07", "npsn": "30301480", "sekolah": "SD NEGERI PARING GULING", "bentuk": "SD", "status": "N", "alamat_jalan": "Jl. NIS.IX B", "lintang": "-3.0226100", "bujur": "115.2181517"}, {"kode_prop": "150000  ", "propinsi": "Prov. Kalimantan Selatan", "kode_kab_kota": "150400  ", "kabupaten_kota": "Kab. Tapin", "kode_kec": "150409  ", "kecamatan": "Kec. Candi Laras Selatan", "id": "207FFB52-30F5-E011-99E0-253AC2F2F84D", "npsn": "30301600", "sekolah": "SD NEGERI MARGASARI ULU", "bentuk": "SD", "status": "N", "alamat_jalan": "Jl. Pambalah Batung RT4", "lintang": "-2.9707000", "bujur": "115.0811000"}, {"kode_prop": "150000  ", "propinsi": "Prov. Kalimantan Selatan", "kode_kab_kota": "150400  ", "kabupaten_kota": "Kab. Tapin", "kode_kec": "150401  ", "kecamatan": "Kec. Binuang", "id": "60ADF452-30F5-E011-ADB5-8DDDFFD6B9F8", "npsn": "30301469", "sekolah": "SD NEGERI PUALAMSARI 1", "bentuk": "SD", "status": "N", "alamat_jalan": "Jl. Pelda Bunawar No 163", "lintang": "-3.1533000", "bujur": "115.1026000"}, {"kode_prop": "150000  ", "propinsi": "Prov. Kalimantan Selatan", "kode_kab_kota": "150400  ", "kabupaten_kota": "Kab. Tapin", "kode_kec": "150406  ", "kecamatan": "Kec. Lokpaikat", "id": "B05EF952-30F5-E011-91CB-79BD70CBAE68", "npsn": "30301546", "sekolah": "SD NEGERI AYUNAN PAPAN", "bentuk": "SD", "status": "N", "alamat_jalan": "Jl. Ayunan Papan Blok B Rt.3", "lintang": "-2.9563000", "bujur": "115.1846000"}, {"kode_prop": "150000  ", "propinsi": "Prov. Kalimantan Selatan", "kode_kab_kota": "150400  ", "kabupaten_kota": "Kab. Tapin", "kode_kec": "150410  ", "kecamatan": "Kec. Candi Laras Utara", "id": "2079FC52-30F5-E011-AA5C-4F0B07F3D012", "npsn": "30301524", "sekolah": "SD NEGERI SUNGAI PUTING", "bentuk": "SD", "status": "N", "alamat_jalan": "sungai puting", "lintang": "-2.9386000", "bujur": "114.9011000"}, {"kode_prop": "150000  ", "propinsi": "Prov. Kalimantan Selatan", "kode_kab_kota": "150400  ", "kabupaten_kota": "Kab. Tapin", "kode_kec": "150401  ", "kecamatan": "Kec. Binuang", "id": "C0FBF452-30F5-E011-8910-E32EF02D2CD3", "npsn": "30301637", "sekolah": "SD NEGERI BINUANG 7", "bentuk": "SD", "status": "N", "alamat_jalan": "Jl. Pln Binuang", "lintang": "-3.1572000", "bujur": "115.0917000"}, {"kode_prop": "150000  ", "propinsi": "Prov. Kalimantan Selatan", "kode_kab_kota": "150400  ", "kabupaten_kota": "Kab. Tapin", "kode_kec": "150409  ", "kecamatan": "Kec. Candi Laras Selatan", "id": "A0A6FB52-30F5-E011-B302-17BF8547D253", "npsn": "30301465", "sekolah": "SD NEGERI PABAUNGAN HILIR 1", "bentuk": "SD", "status": "N", "alamat_jalan": "Jl. Raya Margasari RT.01 Km.22", "lintang": "-2.8525000", "bujur": "115.0013000"}, {"kode_prop": "150000  ", "propinsi": "Prov. Kalimantan Selatan", "kode_kab_kota": "150400  ", "kabupaten_kota": "Kab. Tapin", "kode_kec": "150401  ", "kecamatan": "Kec. Binuang", "id": "90D4F452-30F5-E011-B337-ABE5A7457541", "npsn": "30301435", "sekolah": "SD NEGERI PULAU PINANG 1", "bentuk": "SD", "status": "N", "alamat_jalan": "Jl. A. Yani Km. 91", "lintang": "-3.1039000", "bujur": "115.0857000"}, {"kode_prop": "150000  ", "propinsi": "Prov. Kalimantan Selatan", "kode_kab_kota": "150400  ", "kabupaten_kota": "Kab. Tapin", "kode_kec": "150407  ", "kecamatan": "Kec. Tapin Utara", "id": "80E4AA53-30F5-E011-B7F8-4B780B3FE9C0", "npsn": "30301485", "sekolah": "SMP MUHAMMADIYAH", "bentuk": "SMP", "status": "S", "alamat_jalan": "Jl. A.yani Kupang", "lintang": "-2.9373933", "bujur": "115.1505350"}, {"kode_prop": "150000  ", "propinsi": "Prov. Kalimantan Selatan", "kode_kab_kota": "150400  ", "kabupaten_kota": "Kab. Tapin", "kode_kec": "150407  ", "kecamatan": "Kec. Tapin Utara", "id": "F0CEF952-30F5-E011-A964-ED8EF006E25C", "npsn": "30301427", "sekolah": "SD NEGERI RANTAU KANAN 3", "bentuk": "SD", "status": "N", "alamat_jalan": "Jln. Darussalam  Rt. 09", "lintang": "-2.9327500", "bujur": "115.1471200"}, {"kode_prop": "150000  ", "propinsi": "Prov. Kalimantan Selatan", "kode_kab_kota": "150400  ", "kabupaten_kota": "Kab. Tapin", "kode_kec": "150401  ", "kecamatan": "Kec. Binuang", "id": "50BAF452-30F5-E011-A100-15CEFAFB4C7B", "npsn": "30301629", "sekolah": "SD NEGERI BINUANG 2", "bentuk": "SD", "status": "N", "alamat_jalan": "Jl. Suka Maju", "lintang": "-3.1325000", "bujur": "115.0772000"}, {"kode_prop": "150000  ", "propinsi": "Prov. Kalimantan Selatan", "kode_kab_kota": "150400  ", "kabupaten_kota": "Kab. Tapin", "kode_kec": "150410  ", "kecamatan": "Kec. Candi Laras Utara", "id": "60F6FB52-30F5-E011-8498-35B7A0A662A4", "npsn": "30301631", "sekolah": "SD NEGERI BUAS BUAS 1", "bentuk": "SD", "status": "N", "alamat_jalan": "Jl. Pasar Buas-Buas RT.01", "lintang": "-2.7816000", "bujur": "114.9633000"}, {"kode_prop": "150000  ", "propinsi": "Prov. Kalimantan Selatan", "kode_kab_kota": "150400  ", "kabupaten_kota": "Kab. Tapin", "kode_kec": "150401  ", "kecamatan": "Kec. Binuang", "id": "80109A53-30F5-E011-ABE3-E1CCF44A94E1", "npsn": "30301496", "sekolah": "SMP NEGERI 1 BINUANG", "bentuk": "SMP", "status": "N", "alamat_jalan": "Jalan Serawi", "lintang": "-3.1477000", "bujur": "115.0832000"}, {"kode_prop": "150000  ", "propinsi": "Prov. Kalimantan Selatan", "kode_kab_kota": "150400  ", "kabupaten_kota": "Kab. Tapin", "kode_kec": "150408  ", "kecamatan": "Kec. Bakarangan", "id": "C014FB52-30F5-E011-8EBD-892729296899", "npsn": "30301650", "sekolah": "SD NEGERI GADUNG KERAMAT", "bentuk": "SD", "status": "N", "alamat_jalan": "Jl. Gadung Keramat", "lintang": "-2.9065167", "bujur": "115.1239400"}, {"kode_prop": "150000  ", "propinsi": "Prov. Kalimantan Selatan", "kode_kab_kota": "150400  ", "kabupaten_kota": "Kab. Tapin", "kode_kec": "150403  ", "kecamatan": "Kec. Tapin Tengah", "id": "A00AF752-30F5-E011-BB93-496F160E2F33", "npsn": "30301476", "sekolah": "SD NEGERI PEMATANG KARANGAN", "bentuk": "SD", "status": "N", "alamat_jalan": "Jl. Hidayat", "lintang": "-2.9447000", "bujur": "115.0846000"}, {"kode_prop": "150000  ", "propinsi": "Prov. Kalimantan Selatan", "kode_kab_kota": "150400  ", "kabupaten_kota": "Kab. Tapin", "kode_kec": "150403  ", "kecamatan": "Kec. Tapin Tengah", "id": "6024F752-30F5-E011-A693-5324F64BE14E", "npsn": "30301603", "sekolah": "SD NEGERI KEPAYANG", "bentuk": "SD", "status": "N", "alamat_jalan": "Jl. Hakim Samad", "lintang": "-2.9373000", "bujur": "115.0960000"}, {"kode_prop": "150000  ", "propinsi": "Prov. Kalimantan Selatan", "kode_kab_kota": "150400  ", "kabupaten_kota": "Kab. Tapin", "kode_kec": "150408  ", "kecamatan": "Kec. Bakarangan", "id": "207BFA52-30F5-E011-B76F-F76285AE7A5D", "npsn": "30301643", "sekolah": "SD NEGERI BUNDUNG 1", "bentuk": "SD", "status": "N", "alamat_jalan": "Jl. Bundung", "lintang": "-2.8955600", "bujur": "115.1384617"}, {"kode_prop": "150000  ", "propinsi": "Prov. Kalimantan Selatan", "kode_kab_kota": "150400  ", "kabupaten_kota": "Kab. Tapin", "kode_kec": "150410  ", "kecamatan": "Kec. Candi Laras Utara", "id": "E044FC52-30F5-E011-927D-B91964301E58", "npsn": "30301610", "sekolah": "SD NEGERI KALADAN 1", "bentuk": "SD", "status": "N", "alamat_jalan": "Kaladan Rt.05 Rw.03", "lintang": "-2.7954000", "bujur": "114.9679000"}, {"kode_prop": "150000  ", "propinsi": "Prov. Kalimantan Selatan", "kode_kab_kota": "150400  ", "kabupaten_kota": "Kab. Tapin", "kode_kec": "150402  ", "kecamatan": "Kec. Tapin Selatan", "id": "C09CF652-30F5-E011-A968-937C94AF07A8", "npsn": "30301532", "sekolah": "SD NEGERI TATAKAN 3", "bentuk": "SD", "status": "N", "alamat_jalan": "Jl. Nes 15 Tatakan", "lintang": "-3.0672000", "bujur": "115.1213000"}, {"kode_prop": "150000  ", "propinsi": "Prov. Kalimantan Selatan", "kode_kab_kota": "150400  ", "kabupaten_kota": "Kab. Tapin", "kode_kec": "150407  ", "kecamatan": "Kec. Tapin Utara", "id": "C0939A53-30F5-E011-BB3E-410F59D72D06", "npsn": "30301505", "sekolah": "SMP NEGERI 1 RANTAU", "bentuk": "SMP", "status": "N", "alamat_jalan": "Jl. Brigjend. H. Hasan Basri", "lintang": "-2.9266750", "bujur": "115.1682217"}, {"kode_prop": "150000  ", "propinsi": "Prov. Kalimantan Selatan", "kode_kab_kota": "150400  ", "kabupaten_kota": "Kab. Tapin", "kode_kec": "150411  ", "kecamatan": "Kec. Hatungun", "id": "00279B53-30F5-E011-8B68-07913B781BD0", "npsn": "30301502", "sekolah": "SMP NEGERI 1 HATUNGUN", "bentuk": "SMP", "status": "N", "alamat_jalan": "Jl. R.A. Kartini", "lintang": "-3.1474000", "bujur": "115.1651000"}, {"kode_prop": "150000  ", "propinsi": "Prov. Kalimantan Selatan", "kode_kab_kota": "150400  ", "kabupaten_kota": "Kab. Tapin", "kode_kec": "150409  ", "kecamatan": "Kec. Candi Laras Selatan", "id": "602FFB52-30F5-E011-A332-AD37B32C8729", "npsn": "30301559", "sekolah": "SD NEGERI BERINGIN 1", "bentuk": "SD", "status": "N", "alamat_jalan": "Jl. Baringin - Margasari", "lintang": "-2.8837000", "bujur": "114.9455000"}, {"kode_prop": "150000  ", "propinsi": "Prov. Kalimantan Selatan", "kode_kab_kota": "150400  ", "kabupaten_kota": "Kab. Tapin", "kode_kec": "150412  ", "kecamatan": "Kec. Salam Babaris", "id": "A0F5FC52-30F5-E011-AF6C-E76F9B7BE7AD", "npsn": "30301440", "sekolah": "SD NEGERI SALAM BABARIS 1", "bentuk": "SD", "status": "N", "alamat_jalan": "Jl. Transmigrasi", "lintang": "-3.0498000", "bujur": "115.1804000"}, {"kode_prop": "150000  ", "propinsi": "Prov. Kalimantan Selatan", "kode_kab_kota": "150400  ", "kabupaten_kota": "Kab. Tapin", "kode_kec": "150412  ", "kecamatan": "Kec. Salam Babaris", "id": "0004FD52-30F5-E011-B02A-33400E2B61A2", "npsn": "30301439", "sekolah": "SD NEGERI SALAM BABARIS 2", "bentuk": "SD", "status": "N", "alamat_jalan": "Jl. Transmigrasi No 6 Rt 02/I", "lintang": "-3.0509000", "bujur": "115.1858000"}, {"kode_prop": "150000  ", "propinsi": "Prov. Kalimantan Selatan", "kode_kab_kota": "150400  ", "kabupaten_kota": "Kab. Tapin", "kode_kec": "150403  ", "kecamatan": "Kec. Tapin Tengah", "id": "2073F752-30F5-E011-A579-AD3D1AE993F0", "npsn": "30301550", "sekolah": "SD NEGERI ANDHIKA", "bentuk": "SD", "status": "N", "alamat_jalan": "Jl. Pasar Andhika", "lintang": "-2.9656000", "bujur": "115.0897000"}, {"kode_prop": "150000  ", "propinsi": "Prov. Kalimantan Selatan", "kode_kab_kota": "150400  ", "kabupaten_kota": "Kab. Tapin", "kode_kec": "150410  ", "kecamatan": "Kec. Candi Laras Utara", "id": "2086FC52-30F5-E011-ACAF-55E79F826BD1", "npsn": "30301478", "sekolah": "SD NEGERI PARIOK 2", "bentuk": "SD", "status": "N", "alamat_jalan": "Pariok RT.08 RW.03", "lintang": "-2.8792000", "bujur": "114.9059000"}, {"kode_prop": "150000  ", "propinsi": "Prov. Kalimantan Selatan", "kode_kab_kota": "150400  ", "kabupaten_kota": "Kab. Tapin", "kode_kec": "150411  ", "kecamatan": "Kec. Hatungun", "id": "90A3FD52-30F5-E011-8107-D50F4863B25A", "npsn": "30301545", "sekolah": "SD NEGERI BAGAK", "bentuk": "SD", "status": "N", "alamat_jalan": "Bagak", "lintang": "-3.1610930", "bujur": "115.2157000"}, {"kode_prop": "150000  ", "propinsi": "Prov. Kalimantan Selatan", "kode_kab_kota": "150400  ", "kabupaten_kota": "Kab. Tapin", "kode_kec": "150404  ", "kecamatan": "Kec. Bungur", "id": "C007F852-30F5-E011-9B8C-7518C802B923", "npsn": "30301653", "sekolah": "SD NEGERI BUNGUR", "bentuk": "SD", "status": "N", "alamat_jalan": "Jl. Jendral Sudirman Km 3.5", "lintang": "-2.9612500", "bujur": "115.1509100"}, {"kode_prop": "150000  ", "propinsi": "Prov. Kalimantan Selatan", "kode_kab_kota": "150400  ", "kabupaten_kota": "Kab. Tapin", "kode_kec": "150410  ", "kecamatan": "Kec. Candi Laras Utara", "id": "C0ADFC52-30F5-E011-912E-FBF566FA8A00", "npsn": "30301609", "sekolah": "SD NEGERI KALADAN 2", "bentuk": "SD", "status": "N", "alamat_jalan": "Kaladan Rt.08 Rw.03", "lintang": "-2.9523000", "bujur": "114.8101000"}, {"kode_prop": "150000  ", "propinsi": "Prov. Kalimantan Selatan", "kode_kab_kota": "150400  ", "kabupaten_kota": "Kab. Tapin", "kode_kec": "150408  ", "kecamatan": "Kec. Bakarangan", "id": "00AE9A53-30F5-E011-BF58-ED156DF14C61", "npsn": "30301484", "sekolah": "SMP NEGERI 1 BAKARANGAN", "bentuk": "SMP", "status": "N", "alamat_jalan": "Jl. Tangkawang Baru", "lintang": "-2.9208983", "bujur": "115.1185900"}, {"kode_prop": "150000  ", "propinsi": "Prov. Kalimantan Selatan", "kode_kab_kota": "150400  ", "kabupaten_kota": "Kab. Tapin", "kode_kec": "150402  ", "kecamatan": "Kec. Tapin Selatan", "id": "902DF652-30F5-E011-870F-87DC17CE04BD", "npsn": "30301626", "sekolah": "SD NEGERI LAWAHAN 1", "bentuk": "SD", "status": "N", "alamat_jalan": "Jl. Lawahan", "lintang": "-2.9831000", "bujur": "115.0970000"}, {"kode_prop": "150000  ", "propinsi": "Prov. Kalimantan Selatan", "kode_kab_kota": "150400  ", "kabupaten_kota": "Kab. Tapin", "kode_kec": "150404  ", "kecamatan": "Kec. Bungur", "id": "2057F852-30F5-E011-8DD7-9FA08637D845", "npsn": "30301608", "sekolah": "SD NEGERI KALUMPANG 1", "bentuk": "SD", "status": "N", "alamat_jalan": "Jl. Martha Giri Kalumpang", "lintang": "-2.9955083", "bujur": "115.1795833"}, {"kode_prop": "150000  ", "propinsi": "Prov. Kalimantan Selatan", "kode_kab_kota": "150400  ", "kabupaten_kota": "Kab. Tapin", "kode_kec": "150403  ", "kecamatan": "Kec. Tapin Tengah", "id": "00AAF752-30F5-E011-AB27-DB63907998E2", "npsn": "30301619", "sekolah": "SD NEGERI MANDURIAN HILIR", "bentuk": "SD", "status": "N", "alamat_jalan": "Jl. Kemerdekaan RT.02 RW. 01", "lintang": "-2.9514000", "bujur": "115.1171000"}, {"kode_prop": "150000  ", "propinsi": "Prov. Kalimantan Selatan", "kode_kab_kota": "150400  ", "kabupaten_kota": "Kab. Tapin", "kode_kec": "150402  ", "kecamatan": "Kec. Tapin Selatan", "id": "802A9A53-30F5-E011-B340-FFD2B8CB7304", "npsn": "30301504", "sekolah": "SMP NEGERI 1 TAPIN SELATAN", "bentuk": "SMP", "status": "N", "alamat_jalan": "Jl. Transmigrasi Munggu Kapasan", "lintang": "-3.0083000", "bujur": "115.1340000"}, {"kode_prop": "150000  ", "propinsi": "Prov. Kalimantan Selatan", "kode_kab_kota": "150400  ", "kabupaten_kota": "Kab. Tapin", "kode_kec": "150410  ", "kecamatan": "Kec. Candi Laras Utara", "id": "406CFC52-30F5-E011-8F18-CB2D6EA47843", "npsn": "30301630", "sekolah": "SD NEGERI BUAS BUAS 2", "bentuk": "SD", "status": "N", "alamat_jalan": "Buas-Buas RT. 007 / RW. 003", "lintang": "-2.7498000", "bujur": "114.9346000"}, {"kode_prop": "150000  ", "propinsi": "Prov. Kalimantan Selatan", "kode_kab_kota": "150400  ", "kabupaten_kota": "Kab. Tapin", "kode_kec": "150409  ", "kecamatan": "Kec. Candi Laras Selatan", "id": "B071FB52-30F5-E011-B53A-B754B897461D", "npsn": "30301520", "sekolah": "SD NEGERI SUNGAI RUTAS 2", "bentuk": "SD", "status": "N", "alamat_jalan": "Jl.Rantau- Margasari Km.20 RT.04 RW.02", "lintang": "-2.8572000", "bujur": "115.0171000"}, {"kode_prop": "150000  ", "propinsi": "Prov. Kalimantan Selatan", "kode_kab_kota": "150400  ", "kabupaten_kota": "Kab. Tapin", "kode_kec": "150401  ", "kecamatan": "Kec. Binuang", "id": "A0C7F452-30F5-E011-920B-35E1B3677396", "npsn": "30301641", "sekolah": "SD NEGERI BINUANG 3", "bentuk": "SD", "status": "N", "alamat_jalan": "Jl. Pantai Belanti", "lintang": "-3.1564000", "bujur": "115.0614000"}, {"kode_prop": "150000  ", "propinsi": "Prov. Kalimantan Selatan", "kode_kab_kota": "150400  ", "kabupaten_kota": "Kab. Tapin", "kode_kec": "150409  ", "kecamatan": "Kec. Candi Laras Selatan", "id": "7057FB52-30F5-E011-84C1-177D0DB7AF1E", "npsn": "30301463", "sekolah": "SD NEGERI PABAUNGAN HULU", "bentuk": "SD", "status": "N", "alamat_jalan": "Jl. Margasari Km.21", "lintang": "-2.8530000", "bujur": "115.0075000"}, {"kode_prop": "150000  ", "propinsi": "Prov. Kalimantan Selatan", "kode_kab_kota": "150400  ", "kabupaten_kota": "Kab. Tapin", "kode_kec": "150403  ", "kecamatan": "Kec. Tapin Tengah", "id": "80EBF752-30F5-E011-A351-EF0532DD2C37", "npsn": "30301449", "sekolah": "SD NEGERI RAWA MUNING 2", "bentuk": "SD", "status": "N", "alamat_jalan": "Jl. Jend. Sudirman, UPT Rawa Muning II", "lintang": "-2.9304000", "bujur": "115.0310000"}, {"kode_prop": "150000  ", "propinsi": "Prov. Kalimantan Selatan", "kode_kab_kota": "150400  ", "kabupaten_kota": "Kab. Tapin", "kode_kec": "150403  ", "kecamatan": "Kec. Tapin Tengah", "id": "20C4F752-30F5-E011-951F-2742498271C7", "npsn": "30301614", "sekolah": "SD NEGERI LABUNG 2", "bentuk": "SD", "status": "N", "alamat_jalan": "Jl. Labung Tengah", "lintang": "-2.9636000", "bujur": "115.1168000"}, {"kode_prop": "150000  ", "propinsi": "Prov. Kalimantan Selatan", "kode_kab_kota": "150400  ", "kabupaten_kota": "Kab. Tapin", "kode_kec": "150403  ", "kecamatan": "Kec. Tapin Tengah", "id": "2082F752-30F5-E011-BCD8-E12C211199EC", "npsn": "30301457", "sekolah": "SD NEGERI PANDULANGAN 2", "bentuk": "SD", "status": "N", "alamat_jalan": "Jl. Sungai Harang", "lintang": "-2.9714000", "bujur": "115.1021000"}, {"kode_prop": "150000  ", "propinsi": "Prov. Kalimantan Selatan", "kode_kab_kota": "150400  ", "kabupaten_kota": "Kab. Tapin", "kode_kec": "150401  ", "kecamatan": "Kec. Binuang", "id": "D0C9AA53-30F5-E011-BCE7-DD5EDB9E5245", "npsn": "30311939", "sekolah": "SMP ISLAM IZZUL HASAN", "bentuk": "SMP", "status": "S", "alamat_jalan": "Jl. Ness XII Rt-14", "lintang": "-3.1293000", "bujur": "115.1050000"}, {"kode_prop": "150000  ", "propinsi": "Prov. Kalimantan Selatan", "kode_kab_kota": "150400  ", "kabupaten_kota": "Kab. Tapin", "kode_kec": "150402  ", "kecamatan": "Kec. Tapin Selatan", "id": "B08D01AA-E4B1-429C-BC56-A04DC54FDAD5", "npsn": "30301513", "sekolah": "SDN SWATO TATAKAN 2", "bentuk": "SD", "status": "N", "alamat_jalan": "JL.DATU SANGGUL NES 13", "lintang": "-3.0671000", "bujur": "115.1550000"}, {"kode_prop": "150000  ", "propinsi": "Prov. Kalimantan Selatan", "kode_kab_kota": "150400  ", "kabupaten_kota": "Kab. Tapin", "kode_kec": "150408  ", "kecamatan": "Kec. Bakarangan", "id": "C0AFFA52-30F5-E011-944A-91F288D5196B", "npsn": "30301536", "sekolah": "SD NEGERI TANGKAWANG", "bentuk": "SD", "status": "N", "alamat_jalan": "Jalan Tangkawang", "lintang": "-2.9235750", "bujur": "115.1080183"}, {"kode_prop": "150000  ", "propinsi": "Prov. Kalimantan Selatan", "kode_kab_kota": "150400  ", "kabupaten_kota": "Kab. Tapin", "kode_kec": "150402  ", "kecamatan": "Kec. Tapin Selatan", "id": "0020F652-30F5-E011-9494-73A83CB1A9A8", "npsn": "30301537", "sekolah": "SD NEGERI TANDUI 1", "bentuk": "SD", "status": "N", "alamat_jalan": "Jl. Tameng Karsa", "lintang": "-3.0475000", "bujur": "115.1158000"}, {"kode_prop": "150000  ", "propinsi": "Prov. Kalimantan Selatan", "kode_kab_kota": "150400  ", "kabupaten_kota": "Kab. Tapin", "kode_kec": "150405  ", "kecamatan": "Kec. Piani", "id": "706C9A53-30F5-E011-A316-C52D53D7DB94", "npsn": "30301506", "sekolah": "SMP NEGERI 1 PIANI", "bentuk": "SMP", "status": "N", "alamat_jalan": "Jl. Telaga Minyak", "lintang": "-2.9469000", "bujur": "115.2678000"}, {"kode_prop": "150000  ", "propinsi": "Prov. Kalimantan Selatan", "kode_kab_kota": "150400  ", "kabupaten_kota": "Kab. Tapin", "kode_kec": "150401  ", "kecamatan": "Kec. Binuang", "id": "8016F552-30F5-E011-8BA3-79B15A929401", "npsn": "30301434", "sekolah": "SD NEGERI PULAU PINANG 2", "bentuk": "SD", "status": "N", "alamat_jalan": "JALAN NES XI", "lintang": "-3.1127000", "bujur": "115.0871000"}, {"kode_prop": "150000  ", "propinsi": "Prov. Kalimantan Selatan", "kode_kab_kota": "150400  ", "kabupaten_kota": "Kab. Tapin", "kode_kec": "150412  ", "kecamatan": "Kec. Salam Babaris", "id": "9012FD52-30F5-E011-BE20-31940456E51B", "npsn": "30301438", "sekolah": "SD NEGERI SALAM BABARIS 3", "bentuk": "SD", "status": "N", "alamat_jalan": "Jl. Nes 9A RT. 11 RW. 04", "lintang": "-3.0430000", "bujur": "115.2015000"}, {"kode_prop": "150000  ", "propinsi": "Prov. Kalimantan Selatan", "kode_kab_kota": "150400  ", "kabupaten_kota": "Kab. Tapin", "kode_kec": "150404  ", "kecamatan": "Kec. Bungur", "id": "60529A53-30F5-E011-A010-A9CE8DFA214E", "npsn": "30301497", "sekolah": "SMP NEGERI 1 BUNGUR", "bentuk": "SMP", "status": "N", "alamat_jalan": "Jl. Marthagiri", "lintang": "-3.0013000", "bujur": "115.1947000"}, {"kode_prop": "150000  ", "propinsi": "Prov. Kalimantan Selatan", "kode_kab_kota": "150400  ", "kabupaten_kota": "Kab. Tapin", "kode_kec": "150411  ", "kecamatan": "Kec. Hatungun", "id": "8086FD52-30F5-E011-8E8B-CFB056184DC4", "npsn": "30311829", "sekolah": "SD NEGERI TARUNGIN 2", "bentuk": "SD", "status": "N", "alamat_jalan": "Jl. Karang Jawa RT 01 RW 1", "lintang": "-3.1409000", "bujur": "115.1766000"}, {"kode_prop": "150000  ", "propinsi": "Prov. Kalimantan Selatan", "kode_kab_kota": "150400  ", "kabupaten_kota": "Kab. Tapin", "kode_kec": "150406  ", "kecamatan": "Kec. Lokpaikat", "id": "C099F952-30F5-E011-B1CE-79F56D2075AF", "npsn": "30301432", "sekolah": "SD NEGERI PUNCAK HARAPAN", "bentuk": "SD", "status": "N", "alamat_jalan": "Jl. HTIi Puncak Harapan", "lintang": "-2.8890000", "bujur": "115.2320000"}, {"kode_prop": "150000  ", "propinsi": "Prov. Kalimantan Selatan", "kode_kab_kota": "150400  ", "kabupaten_kota": "Kab. Tapin", "kode_kec": "150403  ", "kecamatan": "Kec. Tapin Tengah", "id": "40459A53-30F5-E011-934E-3B4782CB9D1B", "npsn": "30312956", "sekolah": "SMP NEGERI 2 TAPIN TENGAH", "bentuk": "SMP", "status": "N", "alamat_jalan": "Jl. Jend. Sudirman", "lintang": "-2.9396000", "bujur": "115.0315000"}, {"kode_prop": "150000  ", "propinsi": "Prov. Kalimantan Selatan", "kode_kab_kota": "150400  ", "kabupaten_kota": "Kab. Tapin", "kode_kec": "150401  ", "kecamatan": "Kec. Binuang", "id": "C449FE43-2304-4243-A2B0-7AA567D5175F", "npsn": "30314182", "sekolah": "SMALB RAMAJAYA", "bentuk": "SMLB", "status": "S", "alamat_jalan": "JL. LAMBUNG MANGKURAT BLOK L", "lintang": "-3.1567000", "bujur": "115.0960000"}, {"kode_prop": "150000  ", "propinsi": "Prov. Kalimantan Selatan", "kode_kab_kota": "150400  ", "kabupaten_kota": "Kab. Tapin", "kode_kec": "150409  ", "kecamatan": "Kec. Candi Laras Selatan", "id": "408CFB52-30F5-E011-9FED-0BC6AA5332C8", "npsn": "30301617", "sekolah": "SD NEGERI MARAMPIAU HILIR", "bentuk": "SD", "status": "N", "alamat_jalan": "Marampiau  Hilir Rt.02", "lintang": "-2.8739000", "bujur": "114.9710000"}, {"kode_prop": "150000  ", "propinsi": "Prov. Kalimantan Selatan", "kode_kab_kota": "150400  ", "kabupaten_kota": "Kab. Tapin", "kode_kec": "150407  ", "kecamatan": "Kec. Tapin Utara", "id": "055C605B-BEDC-4D81-B6B6-F10B9FCF6CA4", "npsn": "30301491", "sekolah": "SMAN 1 RANTAU", "bentuk": "SMA", "status": "N", "alamat_jalan": "JL. BRIGJEN. H. HASAN BASRY KM.2 RANTAU", "lintang": "-2.9282250", "bujur": "115.1680500"}, {"kode_prop": "150000  ", "propinsi": "Prov. Kalimantan Selatan", "kode_kab_kota": "150400  ", "kabupaten_kota": "Kab. Tapin", "kode_kec": "150404  ", "kecamatan": "Kec. Bungur", "id": "C02FF852-30F5-E011-A5A3-CB9E6B3A695F", "npsn": "30301528", "sekolah": "SD NEGERI TIMBUNG", "bentuk": "SD", "status": "N", "alamat_jalan": "Timbung", "lintang": "-2.9778067", "bujur": "115.1640200"}, {"kode_prop": "150000  ", "propinsi": "Prov. Kalimantan Selatan", "kode_kab_kota": "150400  ", "kabupaten_kota": "Kab. Tapin", "kode_kec": "150412  ", "kecamatan": "Kec. Salam Babaris", "id": "2030FD52-30F5-E011-8817-9BB5132D1866", "npsn": "30301517", "sekolah": "SD NEGERI SWATO 1", "bentuk": "SD", "status": "N", "alamat_jalan": "Jl. Transmigrasi - Suato Lama", "lintang": "-3.0556000", "bujur": "115.1309000"}, {"kode_prop": "150000  ", "propinsi": "Prov. Kalimantan Selatan", "kode_kab_kota": "150400  ", "kabupaten_kota": "Kab. Tapin", "kode_kec": "150410  ", "kecamatan": "Kec. Candi Laras Utara", "id": "205FFC52-30F5-E011-8C19-A3ECB65B3C52", "npsn": "30301451", "sekolah": "SD NEGERI SAWAJA", "bentuk": "SD", "status": "N", "alamat_jalan": "Sawaja Rt.4 Rw.02", "lintang": "-2.7434000", "bujur": "114.9586000"}, {"kode_prop": "150000  ", "propinsi": "Prov. Kalimantan Selatan", "kode_kab_kota": "150400  ", "kabupaten_kota": "Kab. Tapin", "kode_kec": "150401  ", "kecamatan": "Kec. Binuang", "id": "7099F552-30F5-E011-A896-81A60AD1A1C6", "npsn": "30301635", "sekolah": "SD NEGERI BINUANG 9", "bentuk": "SD", "status": "N", "alamat_jalan": "Jl. Gunung Ulin", "lintang": "-3.1568000", "bujur": "115.1234000"}, {"kode_prop": "150000  ", "propinsi": "Prov. Kalimantan Selatan", "kode_kab_kota": "150400  ", "kabupaten_kota": "Kab. Tapin", "kode_kec": "150402  ", "kecamatan": "Kec. Tapin Selatan", "id": "70E9F552-30F5-E011-A162-ED3E4CBF0113", "npsn": "30301624", "sekolah": "SD NEGERI LAWAHAN CEMPAKA", "bentuk": "SD", "status": "N", "alamat_jalan": "Jl. Lawahan Rt.03", "lintang": "-2.9903000", "bujur": "115.1154000"}, {"kode_prop": "150000  ", "propinsi": "Prov. Kalimantan Selatan", "kode_kab_kota": "150400  ", "kabupaten_kota": "Kab. Tapin", "kode_kec": "150408  ", "kecamatan": "Kec. Bakarangan", "id": "D0A2FA52-30F5-E011-B870-57E162352353", "npsn": "30301543", "sekolah": "SD NEGERI BAKARANGAN 2", "bentuk": "SD", "status": "N", "alamat_jalan": "Jl. Syekh Salman Al Farisi", "lintang": "-2.9258750", "bujur": "115.1240283"}, {"kode_prop": "150000  ", "propinsi": "Prov. Kalimantan Selatan", "kode_kab_kota": "150400  ", "kabupaten_kota": "Kab. Tapin", "kode_kec": "150407  ", "kecamatan": "Kec. Tapin Utara", "id": "206EFA52-30F5-E011-83B1-B3F8569DC9FA", "npsn": "30301428", "sekolah": "SD NEGERI RANGDA MALINGKUNG 5", "bentuk": "SD", "status": "N", "alamat_jalan": "Jl. Rangda", "lintang": "-2.9327867", "bujur": "115.1520783"}, {"kode_prop": "150000  ", "propinsi": "Prov. Kalimantan Selatan", "kode_kab_kota": "150400  ", "kabupaten_kota": "Kab. Tapin", "kode_kec": "150407  ", "kecamatan": "Kec. Tapin Utara", "id": "B0B4F952-30F5-E011-9FEB-1B883D468FC2", "npsn": "30301437", "sekolah": "SD NEGERI RANTAU KIWA 2", "bentuk": "SD", "status": "N", "alamat_jalan": "Jl. Brigjend H. Hasan Basry Km.2", "lintang": "-2.9261117", "bujur": "115.1692367"}, {"kode_prop": "150000  ", "propinsi": "Prov. Kalimantan Selatan", "kode_kab_kota": "150400  ", "kabupaten_kota": "Kab. Tapin", "kode_kec": "150405  ", "kecamatan": "Kec. Piani", "id": "B0CDF852-30F5-E011-961D-2D38C147092E", "npsn": "30301470", "sekolah": "SD NEGERI PIPITAK JAYA 2", "bentuk": "SD", "status": "N", "alamat_jalan": "Jl. Surya Piani Kariaman", "lintang": "-2.9540000", "bujur": "115.3222000"}, {"kode_prop": "150000  ", "propinsi": "Prov. Kalimantan Selatan", "kode_kab_kota": "150400  ", "kabupaten_kota": "Kab. Tapin", "kode_kec": "150402  ", "kecamatan": "Kec. Tapin Selatan", "id": "5072F652-30F5-E011-9984-EB130766D0C8", "npsn": "30301538", "sekolah": "SD NEGERI TAMBARANGAN 3", "bentuk": "SD", "status": "N", "alamat_jalan": "Jl. DESA 18 TAMBARANGAN", "lintang": "-3.0066000", "bujur": "115.1477000"}, {"kode_prop": "150000  ", "propinsi": "Prov. Kalimantan Selatan", "kode_kab_kota": "150400  ", "kabupaten_kota": "Kab. Tapin", "kode_kec": "150411  ", "kecamatan": "Kec. Hatungun", "id": "60ECFD52-30F5-E011-9DCE-55DD8EDFDBAE", "npsn": "30301563", "sekolah": "SD NEGERI BATU HAPU 1", "bentuk": "SD", "status": "N", "alamat_jalan": "Jl.  Wisata Goa Batu Hapu", "lintang": "-3.1326000", "bujur": "115.1733000"}, {"kode_prop": "150000  ", "propinsi": "Prov. Kalimantan Selatan", "kode_kab_kota": "150400  ", "kabupaten_kota": "Kab. Tapin", "kode_kec": "150412  ", "kecamatan": "Kec. Salam Babaris", "id": "20D8FC52-30F5-E011-AD8D-FD98EEE0C744", "npsn": "30301606", "sekolah": "SD NEGERI KEMBANG HABANG 3", "bentuk": "SD", "status": "N", "alamat_jalan": "Jl. Per Nes 14 Kembang Habang Baru RT.06 RW.03", "lintang": "-3.0941000", "bujur": "115.1310000"}, {"kode_prop": "150000  ", "propinsi": "Prov. Kalimantan Selatan", "kode_kab_kota": "150400  ", "kabupaten_kota": "Kab. Tapin", "kode_kec": "150405  ", "kecamatan": "Kec. Piani", "id": "701CF952-30F5-E011-A957-1538B2A880DC", "npsn": "30301564", "sekolah": "SD NEGERI BATU AMPAR", "bentuk": "SD", "status": "N", "alamat_jalan": "Jl. Desa Batu Ampar", "lintang": "-2.9448170", "bujur": "115.3031450"}, {"kode_prop": "150000  ", "propinsi": "Prov. Kalimantan Selatan", "kode_kab_kota": "150400  ", "kabupaten_kota": "Kab. Tapin", "kode_kec": "150401  ", "kecamatan": "Kec. Binuang", "id": "40AAD253-30F5-E011-B653-8B462CF80CD8", "npsn": "30301486", "sekolah": "SMPLB RAMAJAYA TAPIN", "bentuk": "SMPLB", "status": "S", "alamat_jalan": "Jl. Lambung Mangkurat Blok L", "lintang": "-3.1567000", "bujur": "115.0958000"}, {"kode_prop": "150000  ", "propinsi": "Prov. Kalimantan Selatan", "kode_kab_kota": "150400  ", "kabupaten_kota": "Kab. Tapin", "kode_kec": "150407  ", "kecamatan": "Kec. Tapin Utara", "id": "602CFA52-30F5-E011-B920-A33480FFEF07", "npsn": "30301426", "sekolah": "SD NEGERI RANTAU KANAN 2", "bentuk": "SD", "status": "N", "alamat_jalan": "Jl. Pahlawan Rt 01", "lintang": "-2.9259567", "bujur": "115.1513800"}, {"kode_prop": "150000  ", "propinsi": "Prov. Kalimantan Selatan", "kode_kab_kota": "150400  ", "kabupaten_kota": "Kab. Tapin", "kode_kec": "150410  ", "kecamatan": "Kec. Candi Laras Utara", "id": "1038FC52-30F5-E011-94DF-B1CB3FB21D9A", "npsn": "30301519", "sekolah": "SD NEGERI SUNGAI SALAI", "bentuk": "SD", "status": "N", "alamat_jalan": "DESA SUNGAI SALAI RT. V KEC. CLU KAB. TAPIN", "lintang": "-2.9828000", "bujur": "115.0969000"}, {"kode_prop": "150000  ", "propinsi": "Prov. Kalimantan Selatan", "kode_kab_kota": "150400  ", "kabupaten_kota": "Kab. Tapin", "kode_kec": "150411  ", "kecamatan": "Kec. Hatungun", "id": "E0DDFD52-30F5-E011-BE2D-59A2157F7F4E", "npsn": "30311822", "sekolah": "SD NEGERI KEMBANG KUNING", "bentuk": "SD", "status": "N", "alamat_jalan": "Jalan pantai batu", "lintang": "-3.1393650", "bujur": "115.1478900"}, {"kode_prop": "150000  ", "propinsi": "Prov. Kalimantan Selatan", "kode_kab_kota": "150400  ", "kabupaten_kota": "Kab. Tapin", "kode_kec": "150403  ", "kecamatan": "Kec. Tapin Tengah", "id": "EE1653A5-CF10-4D85-986D-D74A6F7E807E", "npsn": "69864631", "sekolah": "SMAN 1 TAPIN TENGAH", "bentuk": "SMA", "status": "N", "alamat_jalan": "Jalan Hakim Samad Km 5", "lintang": "-2.9421750", "bujur": "115.1123040"}, {"kode_prop": "150000  ", "propinsi": "Prov. Kalimantan Selatan", "kode_kab_kota": "150400  ", "kabupaten_kota": "Kab. Tapin", "kode_kec": "150410  ", "kecamatan": "Kec. Candi Laras Utara", "id": "90E29A53-30F5-E011-8469-61D178D2484F", "npsn": "30301508", "sekolah": "SMP NEGERI 1 CANDI LARAS UTARA", "bentuk": "SMP", "status": "N", "alamat_jalan": "Jl. Gusti Libi No.8", "lintang": "-2.8792480", "bujur": "114.9265890"}, {"kode_prop": "150000  ", "propinsi": "Prov. Kalimantan Selatan", "kode_kab_kota": "150400  ", "kabupaten_kota": "Kab. Tapin", "kode_kec": "150404  ", "kecamatan": "Kec. Bungur", "id": "6022F852-30F5-E011-85E0-07477A9CF04E", "npsn": "30301554", "sekolah": "SD NEGERI BANUA PADANG", "bentuk": "SD", "status": "N", "alamat_jalan": "Jl. A. Yani Km 4,5 Rantau", "lintang": "-2.9708567", "bujur": "115.1459950"}, {"kode_prop": "150000  ", "propinsi": "Prov. Kalimantan Selatan", "kode_kab_kota": "150400  ", "kabupaten_kota": "Kab. Tapin", "kode_kec": "150402  ", "kecamatan": "Kec. Tapin Selatan", "id": "7056F652-30F5-E011-9CD9-271134750D60", "npsn": "30301529", "sekolah": "SD NEGERI TIMBAAN 2", "bentuk": "SD", "status": "N", "alamat_jalan": "Timbaan", "lintang": "-2.9707000", "bujur": "115.1104000"}, {"kode_prop": "150000  ", "propinsi": "Prov. Kalimantan Selatan", "kode_kab_kota": "150400  ", "kabupaten_kota": "Kab. Tapin", "kode_kec": "150410  ", "kecamatan": "Kec. Candi Laras Utara", "id": "90DBFB52-30F5-E011-B712-D3E798FD8D50", "npsn": "30301616", "sekolah": "SD NEGERI MARGASARI ILIR 1", "bentuk": "SD", "status": "N", "alamat_jalan": "Jl. Pendidikan No.75 Rt.01", "lintang": "-2.8798000", "bujur": "114.9338000"}, {"kode_prop": "150000  ", "propinsi": "Prov. Kalimantan Selatan", "kode_kab_kota": "150400  ", "kabupaten_kota": "Kab. Tapin", "kode_kec": "150406  ", "kecamatan": "Kec. Lokpaikat", "id": "80869A53-30F5-E011-8734-4D59B7F11F8E", "npsn": "30301507", "sekolah": "SMP NEGERI 1 LOKPAIKAT", "bentuk": "SMP", "status": "N", "alamat_jalan": "Jl. Brigjend. H. Hasan Basri", "lintang": "-2.9027000", "bujur": "115.2128000"}, {"kode_prop": "150000  ", "propinsi": "Prov. Kalimantan Selatan", "kode_kab_kota": "150400  ", "kabupaten_kota": "Kab. Tapin", "kode_kec": "150404  ", "kecamatan": "Kec. Bungur", "id": "C03CF852-30F5-E011-9614-D7EB80999B4D", "npsn": "30301454", "sekolah": "SD NEGERI KALUMPANG 3", "bentuk": "SD", "status": "N", "alamat_jalan": "Jl. Martagiri Pantai Walang", "lintang": "-3.0062000", "bujur": "115.2133000"}, {"kode_prop": "150000  ", "propinsi": "Prov. Kalimantan Selatan", "kode_kab_kota": "150400  ", "kabupaten_kota": "Kab. Tapin", "kode_kec": "150411  ", "kecamatan": "Kec. Hatungun", "id": "2078FD52-30F5-E011-BCA5-C7B72E1C3857", "npsn": "30301535", "sekolah": "SD NEGERI TARUNGIN 1", "bentuk": "SD", "status": "N", "alamat_jalan": "Jl. Bina Nusa", "lintang": "-3.1495000", "bujur": "115.1911000"}, {"kode_prop": "150000  ", "propinsi": "Prov. Kalimantan Selatan", "kode_kab_kota": "150400  ", "kabupaten_kota": "Kab. Tapin", "kode_kec": "150401  ", "kecamatan": "Kec. Binuang", "id": "4030F552-30F5-E011-9BAF-45DD8AE4EEE8", "npsn": "30301638", "sekolah": "SD NEGERI BINUANG 6", "bentuk": "SD", "status": "N", "alamat_jalan": "Jl.A.Yani KM.86 Serawi Binuang", "lintang": "-3.1501000", "bujur": "115.0817000"}, {"kode_prop": "150000  ", "propinsi": "Prov. Kalimantan Selatan", "kode_kab_kota": "150400  ", "kabupaten_kota": "Kab. Tapin", "kode_kec": "150402  ", "kecamatan": "Kec. Tapin Selatan", "id": "40B9F652-30F5-E011-8012-D7BFDE7B7474", "npsn": "30301645", "sekolah": "SD NEGERI HARAPAN MASA 2", "bentuk": "SD", "status": "N", "alamat_jalan": "Jl. K.H. Mahyudin", "lintang": "-2.9896000", "bujur": "115.1529000"}, {"kode_prop": "150000  ", "propinsi": "Prov. Kalimantan Selatan", "kode_kab_kota": "150400  ", "kabupaten_kota": "Kab. Tapin", "kode_kec": "150403  ", "kecamatan": "Kec. Tapin Tengah", "id": "40DEF752-30F5-E011-B9BB-776D3A42697E", "npsn": "30301450", "sekolah": "SD NEGERI RAWA MUNING 1", "bentuk": "SD", "status": "N", "alamat_jalan": "Jl. Transmigrasi Rawamuning", "lintang": "-2.9629000", "bujur": "115.0547000"}, {"kode_prop": "150000  ", "propinsi": "Prov. Kalimantan Selatan", "kode_kab_kota": "150400  ", "kabupaten_kota": "Kab. Tapin", "kode_kec": "150410  ", "kecamatan": "Kec. Candi Laras Utara", "id": "8003FC52-30F5-E011-BEA8-AB37DBE584D3", "npsn": "30301479", "sekolah": "SD NEGERI PARIOK 1", "bentuk": "SD", "status": "N", "alamat_jalan": "Jl. Gusti Libi Rt.04", "lintang": "-2.8747000", "bujur": "114.9157000"}, {"kode_prop": "150000  ", "propinsi": "Prov. Kalimantan Selatan", "kode_kab_kota": "150400  ", "kabupaten_kota": "Kab. Tapin", "kode_kec": "150403  ", "kecamatan": "Kec. Tapin Tengah", "id": "E09CF752-30F5-E011-B86B-4B143E543EDE", "npsn": "30301611", "sekolah": "SD NEGERI HIYUNG 2", "bentuk": "SD", "status": "N", "alamat_jalan": "Jl. Hakim Samad Hiyung", "lintang": "-2.9147000", "bujur": "115.0636000"}, {"kode_prop": "150000  ", "propinsi": "Prov. Kalimantan Selatan", "kode_kab_kota": "150400  ", "kabupaten_kota": "Kab. Tapin", "kode_kec": "150412  ", "kecamatan": "Kec. Salam Babaris", "id": "803EFD52-30F5-E011-B0DF-8593E2BFCE01", "npsn": "30301516", "sekolah": "SD NEGERI SWATO 2", "bentuk": "SD", "status": "N", "alamat_jalan": "Jl.Transmigrasi-Suato Lama", "lintang": "-3.0555000", "bujur": "115.1310000"}, {"kode_prop": "150000  ", "propinsi": "Prov. Kalimantan Selatan", "kode_kab_kota": "150400  ", "kabupaten_kota": "Kab. Tapin", "kode_kec": "150405  ", "kecamatan": "Kec. Piani", "id": "E0DAF852-30F5-E011-9DF0-73863259520A", "npsn": "30301471", "sekolah": "SD NEGERI PIPITAK JAYA 1", "bentuk": "SD", "status": "N", "alamat_jalan": "Jl. Taniti Kapuh", "lintang": "-2.9502000", "bujur": "115.3601000"}, {"kode_prop": "150000  ", "propinsi": "Prov. Kalimantan Selatan", "kode_kab_kota": "150400  ", "kabupaten_kota": "Kab. Tapin", "kode_kec": "150408  ", "kecamatan": "Kec. Bakarangan", "id": "E0ECFA52-30F5-E011-9FC8-7B405F53B368", "npsn": "30301477", "sekolah": "SD NEGERI PAUL", "bentuk": "SD", "status": "N", "alamat_jalan": "Jl. Gerilya Desa Paul Kecamatan Bakarangan", "lintang": "-2.9178783", "bujur": "115.1370867"}, {"kode_prop": "150000  ", "propinsi": "Prov. Kalimantan Selatan", "kode_kab_kota": "150400  ", "kabupaten_kota": "Kab. Tapin", "kode_kec": "150401  ", "kecamatan": "Kec. Binuang", "id": "8064F552-30F5-E011-8A25-83B396685AA0", "npsn": "30301433", "sekolah": "SD NEGERI PULAU PINANG UTARA", "bentuk": "SD", "status": "N", "alamat_jalan": "Jl. Sido Makmur", "lintang": "-3.0918000", "bujur": "115.0953000"}, {"kode_prop": "150000  ", "propinsi": "Prov. Kalimantan Selatan", "kode_kab_kota": "150400  ", "kabupaten_kota": "Kab. Tapin", "kode_kec": "150403  ", "kecamatan": "Kec. Tapin Tengah", "id": "70E3F652-30F5-E011-8DCA-2F860C21C3BC", "npsn": "30301527", "sekolah": "SD NEGERI TIRIK", "bentuk": "SD", "status": "N", "alamat_jalan": "Jl. Garuda Rt.iv Rw.02", "lintang": "-2.9659000", "bujur": "115.1369000"}, {"kode_prop": "150000  ", "propinsi": "Prov. Kalimantan Selatan", "kode_kab_kota": "150400  ", "kabupaten_kota": "Kab. Tapin", "kode_kec": "150402  ", "kecamatan": "Kec. Tapin Selatan", "id": "E0AAF652-30F5-E011-BAEB-1BAE328D4B75", "npsn": "30301533", "sekolah": "SD NEGERI TATAKAN 2", "bentuk": "SD", "status": "N", "alamat_jalan": "Tatakan", "lintang": "-3.0733000", "bujur": "115.1055000"}, {"kode_prop": "150000  ", "propinsi": "Prov. Kalimantan Selatan", "kode_kab_kota": "150400  ", "kabupaten_kota": "Kab. Tapin", "kode_kec": "150410  ", "kecamatan": "Kec. Candi Laras Utara", "id": "C010FC52-30F5-E011-AA4B-15429A4115B4", "npsn": "30301447", "sekolah": "SD NEGERI RAWANA HILIR", "bentuk": "SD", "status": "N", "alamat_jalan": "Desa Rawana Hilir", "lintang": "-2.8013000", "bujur": "114.9335000"}, {"kode_prop": "150000  ", "propinsi": "Prov. Kalimantan Selatan", "kode_kab_kota": "150400  ", "kabupaten_kota": "Kab. Tapin", "kode_kec": "150401  ", "kecamatan": "Kec. Binuang", "id": "D0EEF452-30F5-E011-BD44-1352D016D3B4", "npsn": "30301639", "sekolah": "SD NEGERI BINUANG 5", "bentuk": "SD", "status": "N", "alamat_jalan": "Jl. Tapioka", "lintang": "-3.1544000", "bujur": "115.0915000"}, {"kode_prop": "150000  ", "propinsi": "Prov. Kalimantan Selatan", "kode_kab_kota": "150400  ", "kabupaten_kota": "Kab. Tapin", "kode_kec": "150404  ", "kecamatan": "Kec. Bungur", "id": "E098F852-30F5-E011-80C0-E999D30D3788", "npsn": "30301423", "sekolah": "SD NEGERI RANTAU BUJUR 1", "bentuk": "SD", "status": "N", "alamat_jalan": "Jl. Limpana", "lintang": "-3.0322000", "bujur": "115.2181000"}, {"kode_prop": "150000  ", "propinsi": "Prov. Kalimantan Selatan", "kode_kab_kota": "150400  ", "kabupaten_kota": "Kab. Tapin", "kode_kec": "150408  ", "kecamatan": "Kec. Bakarangan", "id": "8095FA52-30F5-E011-9B39-FF8A6ADF5ED6", "npsn": "30301544", "sekolah": "SD NEGERI BAKARANGAN 1", "bentuk": "SD", "status": "N", "alamat_jalan": "Jl. Syekh Salman Al Farisi", "lintang": "-2.9207517", "bujur": "115.1205533"}, {"kode_prop": "150000  ", "propinsi": "Prov. Kalimantan Selatan", "kode_kab_kota": "150400  ", "kabupaten_kota": "Kab. Tapin", "kode_kec": "150401  ", "kecamatan": "Kec. Binuang", "id": "ED762B57-004C-4E91-8406-801EFE3C1D40", "npsn": "30301494", "sekolah": "SMAS KARTIKA V-2 BINUANG", "bentuk": "SMA", "status": "S", "alamat_jalan": "JL. RAYA TIMUR BINUANG", "lintang": "-3.1569000", "bujur": "115.0909000"}, {"kode_prop": "150000  ", "propinsi": "Prov. Kalimantan Selatan", "kode_kab_kota": "150400  ", "kabupaten_kota": "Kab. Tapin", "kode_kec": "150402  ", "kecamatan": "Kec. Tapin Selatan", "id": "E0B3F552-30F5-E011-955B-410333E9E7E6", "npsn": "30301526", "sekolah": "SD NEGERI TAMBARANGAN 2", "bentuk": "SD", "status": "N", "alamat_jalan": "Jl. Munggu Raya", "lintang": "-3.0012000", "bujur": "115.1286000"}, {"kode_prop": "150000  ", "propinsi": "Prov. Kalimantan Selatan", "kode_kab_kota": "150400  ", "kabupaten_kota": "Kab. Tapin", "kode_kec": "150401  ", "kecamatan": "Kec. Binuang", "id": "602FD353-30F5-E011-BBF8-1923868CA5F1", "npsn": "30314040", "sekolah": "SLBN PUALAMSARI", "bentuk": "SDLB", "status": "N", "alamat_jalan": "Jl. Lambung Mangkurat Pualamsari", "lintang": "-3.1566820", "bujur": "115.0960000"}, {"kode_prop": "150000  ", "propinsi": "Prov. Kalimantan Selatan", "kode_kab_kota": "150400  ", "kabupaten_kota": "Kab. Tapin", "kode_kec": "150406  ", "kecamatan": "Kec. Lokpaikat", "id": "A036F952-30F5-E011-AF5C-07DC9B8F7125", "npsn": "30301634", "sekolah": "SD NEGERI BITAHAN 1", "bentuk": "SD", "status": "N", "alamat_jalan": "Jl. Brigjen Hasan Basri Km. 3,5", "lintang": "-2.9192000", "bujur": "115.1817000"}, {"kode_prop": "150000  ", "propinsi": "Prov. Kalimantan Selatan", "kode_kab_kota": "150400  ", "kabupaten_kota": "Kab. Tapin", "kode_kec": "150405  ", "kecamatan": "Kec. Piani", "id": "40C0F852-30F5-E011-A984-E5E75AF434B1", "npsn": "30301566", "sekolah": "SD NEGERI BARAMBAN", "bentuk": "SD", "status": "N", "alamat_jalan": "Jl. Cendrawasih", "lintang": "-2.9643170", "bujur": "115.2626000"}, {"kode_prop": "150000  ", "propinsi": "Prov. Kalimantan Selatan", "kode_kab_kota": "150400  ", "kabupaten_kota": "Kab. Tapin", "kode_kec": "150402  ", "kecamatan": "Kec. Tapin Selatan", "id": "003BF652-30F5-E011-8B2F-DFD741333873", "npsn": "30301482", "sekolah": "SD NEGERI SAWANG", "bentuk": "SD", "status": "N", "alamat_jalan": "Jl. Simpang Jambu", "lintang": "-2.9896000", "bujur": "115.1308000"}, {"kode_prop": "150000  ", "propinsi": "Prov. Kalimantan Selatan", "kode_kab_kota": "150400  ", "kabupaten_kota": "Kab. Tapin", "kode_kec": "150410  ", "kecamatan": "Kec. Candi Laras Utara", "id": "70A0FC52-30F5-E011-978A-B3FD40BA4A1E", "npsn": "30301642", "sekolah": "SD NEGERI BUAS BUAS HILIR", "bentuk": "SD", "status": "N", "alamat_jalan": "Ds.BUAS-BUAS HILIR", "lintang": "-2.6662000", "bujur": "114.8912000"}, {"kode_prop": "150000  ", "propinsi": "Prov. Kalimantan Selatan", "kode_kab_kota": "150400  ", "kabupaten_kota": "Kab. Tapin", "kode_kec": "150405  ", "kecamatan": "Kec. Piani", "id": "80E8F852-30F5-E011-8735-A1FDB363CA5B", "npsn": "30301647", "sekolah": "SD NEGERI HARAKIT", "bentuk": "SD", "status": "N", "alamat_jalan": "Jl.Batu Kursi RT.01 RW.01 No. 006", "lintang": "-2.9473000", "bujur": "115.3816000"}, {"kode_prop": "150000  ", "propinsi": "Prov. Kalimantan Selatan", "kode_kab_kota": "150400  ", "kabupaten_kota": "Kab. Tapin", "kode_kec": "150409  ", "kecamatan": "Kec. Candi Laras Selatan", "id": "803CFB52-30F5-E011-BD1D-730C8EF04A8F", "npsn": "30301560", "sekolah": "SD NEGERI BAULIN", "bentuk": "SD", "status": "N", "alamat_jalan": "Desa Baulin Rt 05", "lintang": "-2.8043000", "bujur": "115.0242000"}]}